Workbook

Sheet Input (AC)
A1: year | B1: summer_on-peak_usdperkWh | C1: summer_off-peak_usdperkWh | D1: winter_on-peak_usdperkWh | E1: winter_off-peak_usdperkWh | F1: shoulder_on-peak_usdperkWh | G1: shoulder_off-peak_usdperkWh | H1: summer_gener_capacity_usdperkW-yr | I1: summer_td_usdperkW-yr | J1: winter_gener_capacity_usdperkW-yr | K1: winter_td_usdperkW-yr | L1: natural_gas_usdperMMBtu | M1: res_fuel_oil_usdperMMBtu | N1: com_fuel_oil_usdperMMBtu | O1: ind_fuel_oil_usdperMMBtu | P1: res_propane_usdperMMBtu | Q1: com_propane_usdperMMBtu | R1: ind_propane_usdperMMBtu | S1: diesel_transportation_usdperMMBtu | T1: gasoline_transportation_usdperMMBtu | U1: water_usdpergallon | V1: electricity_retail_prices_res_usdperkwh | W1: electricity_retail_prices_commercial_usdperkwh | X1: electricity_retail_prices_industrial_usdperkwh | Y1: natural_gas_retail_prices_res_usdpermmbtu | Z1: natural_gas_retail_prices_commercial_usdpermmbtu | AA1: natural_gas_retail_prices_industrial_usdpermmbtu | AB1: heating_oil_retail_prices_res_usdpermmbtu | AC1: heating_oil_retail_prices_commercial_usdpermmbtu | AD1: heating_oil_retail_prices_industrial_usdpermmbtu | AE1: summer_on-peak_usdperkWh_carbon | AF1: summer_off-peak_usdperkWh_carbon | AG1: winter_on-peak_usdperkWh_carbon | AH1: winter_off-peak_usdperkWh_carbon | AI1: shoulder_on-peak_usdperkWh_carbon | AJ1: shoulder_off-peak_usdperkWh_carbon | AK1: natural_gas_usdperMMBtu_carbon | AL1: res_fuel_oil_usdperMMBtu_carbon | AM1: com_fuel_oil_usdperMMBtu_carbon | AN1: ind_fuel_oil_usdperMMBtu_carbon | AO1: res_propane_usdperMMBtu_carbon | AP1: com_propane_usdperMMBtu_carbon | AQ1: ind_propane_usdperMMBtu_carbon | AR1: diesel_transportation_usdperMMBtu_carbon | AS1: gasoline_transportation_usdperMMBtu_carbon | AT1: summer_on-peak_usdperkWh_n2o | AU1: summer_off-peak_usdperkWh_n2o | AV1: winter_on-peak_usdperkWh_n2o | AW1: winter_off-peak_usdperkWh_n2o | AX1: shoulder_on-peak_usdperkWh_n2o | AY1: shoulder_off-peak_usdperkWh_n2o | AZ1: natural_gas_usdperMMBtu_n2o | BA1: res_fuel_oil_usdperMMBtu_n2o | BB1: com_fuel_oil_usdperMMBtu_n2o | BC1: ind_fuel_oil_usdperMMBtu_n2o | BD1: res_propane_usdperMMBtu_n2o | BE1: com_propane_usdperMMBtu_n2o | BF1: ind_propane_usdperMMBtu_n2o | BG1: diesel_transportation_usdperMMBtu_n2o | BH1: gasoline_transportation_usdperMMBtu_n2o | BI1: summer_on-peak_usdperkWh_ch4 | BJ1: summer_off-peak_usdperkWh_ch4 | BK1: winter_on-peak_usdperkWh_ch4 | BL1: winter_off-peak_usdperkWh_ch4 | BM1: shoulder_on-peak_usdperkWh_ch4 | BN1: shoulder_off-peak_usdperkWh_ch4 | BO1: natural_gas_usdperMMBtu_ch4 | BP1: res_fuel_oil_usdperMMBtu_ch4 | BQ1: com_fuel_oil_usdperMMBtu_ch4 | BR1: ind_fuel_oil_usdperMMBtu_ch4 | BS1: res_propane_usdperMMBtu_ch4 | BT1: com_propane_usdperMMBtu_ch4 | BU1: ind_propane_usdperMMBtu_ch4 | BV1: diesel_transportation_usdperMMBtu_ch4 | BW1: gasoline_transportation_usdperMMBtu_ch4
A2: 1 | B2: 0.06 | C2: 0.04 | D2: 0.06 | E2: 0.04 | F2: 0.04 | G2: 0.04 | H2: 89.69 | I2: 18.6 | J2: 0 | K2: 0 | L2: 5.62 | M2: 24.68 | N2: 18.71 | O2: 18.71 | P2: 25.38 | Q2: 22.83 | R2: 22.83 | S2: 28.12 | T2: 27.09 | U2: 0.02 | V2: 0.2 | W2: 0.14 | X2: 0.08 | Y2: 11.26 | Z2: 9.77 | AA2: 7.91 | AB2: 24.68 | AC2: 18.71 | AD2: 18.71 | AE2: 0.077749014 | AF2: 0.075741179 | AG2: 0.084995875 | AH2: 0.08228085 | AI2: 0.05206803 | AJ2: 0.05206803 | AK2: 14.594126 | AL2: 20.342661 | AM2: 20.342661 | AN2: 20.342661 | AO2: 17.292362 | AP2: 17.292362 | AQ2: 17.292362 | AR2: 20.441367 | AS2: 20.08863 | AT2: 0.000149 | AU2: 0.000158 | AV2: 0.000193 | AW2: 0.000199 | AX2: 9.04e-05 | AY2: 9.04e-05 | AZ2: 0.007866672 | BA2: 0.047200029 | BB2: 0.0472 | BC2: 0.0472 | BD2: 0.047200029 | BE2: 0.0472 | BF2: 0.0472 | BG2: 0.047200029 | BH2: 0.047200029 | BI2: 0.004387404 | BJ2: 0.003927791 | BK2: 0.004432337 | BL2: 0.004162093 | BM2: 0.003112023 | BN2: 0.003112023 | BO2: 0.002687809 | BP2: 0.008063428 | BQ2: 0.0080634 | BR2: 0.0080634 | BS2: 0.008063428 | BT2: 0.0080634 | BU2: 0.0080634 | BV2: 0.008063428 | BW2: 0.008063428
A3: 2 | B3: 0.06 | C3: 0.05 | D3: 0.06 | E3: 0.05 | F3: 0.04 | G3: 0.04 | H3: 49.6 | I3: 18.32 | J3: 0 | K3: 0 | L3: 4.73 | M3: 25 | N3: 18.24 | O3: 18.19 | P3: 25.19 | Q3: 22.61 | R3: 22.51 | S3: 28.19 | T3: 26.53 | U3: 0.02 | V3: 0.21 | W3: 0.14 | X3: 0.08 | Y3: 10.72 | Z3: 9.96 | AA3: 7.69 | AB3: 25 | AC3: 18.24 | AD3: 18.19 | AE3: 0.080499329 | AF3: 0.079677276 | AG3: 0.089508689 | AH3: 0.086465299 | AI3: 0.054188785 | AJ3: 0.054188785 | AK3: 14.865645 | AL3: 20.721129 | AM3: 20.721129 | AN3: 20.721129 | AO3: 17.61408 | AP3: 17.61408 | AQ3: 17.61408 | AR3: 20.821671 | AS3: 20.462372 | AT3: 0.000163 | AU3: 0.000175 | AV3: 0.000209 | AW3: 0.000211 | AX3: 9.71e-05 | AY3: 9.71e-05 | AZ3: 0.008023514 | BA3: 0.048141082 | BB3: 0.0481411 | BC3: 0.0481411 | BD3: 0.048141082 | BE3: 0.0481411 | BF3: 0.0481411 | BG3: 0.048141082 | BH3: 0.048141082 | BI3: 0.004409191 | BJ3: 0.004008308 | BK3: 0.004559877 | BL3: 0.004307253 | BM3: 0.003165647 | BN3: 0.003165647 | BO3: 0.002783757 | BP3: 0.00835127 | BQ3: 0.0083513 | BR3: 0.0083513 | BS3: 0.00835127 | BT3: 0.0083513 | BU3: 0.0083513 | BV3: 0.00835127 | BW3: 0.00835127
A4: 3 | B4: 0.06 | C4: 0.05 | D4: 0.06 | E4: 0.05 | F4: 0.04 | G4: 0.04 | H4: 42.36 | I4: 18.31 | J4: 0 | K4: 0 | L4: 4.71 | M4: 25.57 | N4: 17.97 | O4: 17.87 | P4: 25.19 | Q4: 22.75 | R4: 22.7 | S4: 28.53 | T4: 26.25 | U4: 0.02 | V4: 0.21 | W4: 0.14 | X4: 0.08 | Y4: 10.38 | Z4: 10.34 | AA4: 7.76 | AB4: 25.57 | AC4: 17.97 | AD4: 17.87 | AE4: 0.083297273 | AF4: 0.083705682 | AG4: 0.09412859 | AH4: 0.090746684 | AI4: 0.056351623 | AJ4: 0.056351623 | AK4: 15.137164 | AL4: 21.099597 | AM4: 21.099597 | AN4: 21.099597 | AO4: 17.935799 | AP4: 17.935799 | AQ4: 17.935799 | AR4: 21.201976 | AS4: 20.836114 | AT4: 0.000177 | AU4: 0.000192 | AV4: 0.000224 | AW4: 0.000223 | AX4: 0.000104 | AY4: 0.000104 | AZ4: 0.008180356 | BA4: 0.049082136 | BB4: 0.0490821 | BC4: 0.0490821 | BD4: 0.049082136 | BE4: 0.0490821 | BF4: 0.0490821 | BG4: 0.049082136 | BH4: 0.049082136 | BI4: 0.004423647 | BJ4: 0.004086524 | BK4: 0.004687384 | BL4: 0.004454156 | BM4: 0.003216739 | BN4: 0.003216739 | BO4: 0.002880984 | BP4: 0.008642951 | BQ4: 0.008643 | BR4: 0.008643 | BS4: 0.008642951 | BT4: 0.008643 | BU4: 0.008643 | BV4: 0.008642951 | BW4: 0.008642951
A5: 4 | B5: 0.06 | C5: 0.05 | D5: 0.06 | E5: 0.05 | F5: 0.04 | G5: 0.04 | H5: 63.21 | I5: 18.3 | J5: 0 | K5: 0 | L5: 4.59 | M5: 26.19 | N5: 17.72 | O5: 17.57 | P5: 25.4 | Q5: 23.11 | R5: 23.23 | S5: 28.89 | T5: 25.94 | U5: 0.02 | V5: 0.22 | W5: 0.14 | X5: 0.08 | Y5: 10.19 | Z5: 10.84 | AA5: 7.94 | AB5: 26.19 | AC5: 17.72 | AD5: 17.57 | AE5: 0.085763361 | AF5: 0.087439496 | AG5: 0.09842009 | AH5: 0.094705953 | AI5: 0.058298587 | AJ5: 0.058298587 | AK5: 15.340803 | AL5: 21.383448 | AM5: 21.383448 | AN5: 21.383448 | AO5: 18.177088 | AP5: 18.177088 | AQ5: 18.177088 | AR5: 21.487204 | AS5: 21.116421 | AT5: 0.000192 | AU5: 0.00021 | AV5: 0.00024 | AW5: 0.000236 | AX5: 0.000111 | AY5: 0.000111 | AZ5: 0.00833707 | BA5: 0.050022421 | BB5: 0.0500224 | BC5: 0.0500224 | BD5: 0.050022421 | BE5: 0.0500224 | BF5: 0.0500224 | BG5: 0.050022421 | BH5: 0.050022421 | BI5: 0.004426783 | BJ5: 0.004158783 | BK5: 0.00481068 | BL5: 0.004598845 | BM5: 0.003262414 | BN5: 0.003262414 | BO5: 0.002976931 | BP5: 0.008930793 | BQ5: 0.0089308 | BR5: 0.0089308 | BS5: 0.008930793 | BT5: 0.0089308 | BU5: 0.0089308 | BV5: 0.008930793 | BW5: 0.008930793
A6: 5 | B6: 0.07 | C6: 0.05 | D6: 0.07 | E6: 0.05 | F6: 0.04 | G6: 0.04 | H6: 57.55 | I6: 18.29 | J6: 0 | K6: 0 | L6: 5.02 | M6: 26.88 | N6: 17.5 | O6: 17.3 | P6: 25.8 | Q6: 23.63 | R6: 23.99 | S6: 29.3 | T6: 26 | U6: 0.02 | V6: 0.22 | W6: 0.15 | X6: 0.08 | Y6: 9.98 | Z6: 11.31 | AA6: 8.15 | AB6: 26.88 | AC6: 17.5 | AD6: 17.3 | AE6: 0.088650607 | AF6: 0.091640981 | AG6: 0.10324078 | AH6: 0.099169094 | AI6: 0.060540333 | AJ6: 0.060540333 | AK6: 15.612321 | AL6: 21.761916 | AM6: 21.761916 | AN6: 21.761916 | AO6: 18.498806 | AP6: 18.498806 | AQ6: 18.498806 | AR6: 21.867509 | AS6: 21.490163 | AT6: 0.000208 | AU6: 0.000228 | AV6: 0.000257 | AW6: 0.000249 | AX6: 0.000119 | AY6: 0.000119 | AZ6: 0.008493912 | BA6: 0.050963474 | BB6: 0.0509635 | BC6: 0.0509635 | BD6: 0.050963474 | BE6: 0.0509635 | BF6: 0.0509635 | BG6: 0.050963474 | BH6: 0.050963474 | BI6: 0.004422464 | BJ6: 0.004228687 | BK6: 0.004933914 | BL6: 0.004745273 | BM6: 0.003305503 | BN6: 0.003305503 | BO6: 0.003074158 | BP6: 0.009222474 | BQ6: 0.0092225 | BR6: 0.0092225 | BS6: 0.009222474 | BT6: 0.0092225 | BU6: 0.0092225 | BV6: 0.009222474 | BW6: 0.009222474
A7: 6 | B7: 0.07 | C7: 0.05 | D7: 0.07 | E7: 0.05 | F7: 0.04 | G7: 0.04 | H7: 60.93 | I7: 18.3 | J7: 0 | K7: 0 | L7: 5.02 | M7: 26.98 | N7: 17.56 | O7: 17.36 | P7: 26.27 | Q7: 24.12 | R7: 24.72 | S7: 29.38 | T7: 26.05 | U7: 0.02 | V7: 0.22 | W7: 0.15 | X7: 0.08 | Y7: 10.2 | Z7: 11.51 | AA7: 8.37 | AB7: 26.98 | AC7: 17.56 | AD7: 17.36 | AE7: 0.079481004 | AF7: 0.082219088 | AG7: 0.093202197 | AH7: 0.088827392 | AI7: 0.052915773 | AJ7: 0.052915773 | AK7: 15.88384 | AL7: 22.140385 | AM7: 22.140385 | AN7: 22.140385 | AO7: 18.820524 | AP7: 18.820524 | AQ7: 18.820524 | AR7: 22.247813 | AS7: 21.863905 | AT7: 0.000176 | AU7: 0.000193 | AV7: 0.000218 | AW7: 0.00021 | AX7: 9.97e-05 | AY7: 9.97e-05 | AZ7: 0.008653825 | BA7: 0.051922949 | BB7: 0.0519229 | BC7: 0.0519229 | BD7: 0.051922949 | BE7: 0.0519229 | BF7: 0.0519229 | BG7: 0.051922949 | BH7: 0.051922949 | BI7: 0.004132915 | BJ7: 0.003960091 | BK7: 0.00467377 | BL7: 0.004448578 | BM7: 0.002984728 | BN7: 0.002984728 | BO7: 0.003185457 | BP7: 0.009556371 | BQ7: 0.0095564 | BR7: 0.0095564 | BS7: 0.009556371 | BT7: 0.0095564 | BU7: 0.0095564 | BV7: 0.009556371 | BW7: 0.009556371
A8: 7 | B8: 0.06 | C8: 0.05 | D8: 0.06 | E8: 0.05 | F8: 0.04 | G8: 0.04 | H8: 74.26 | I8: 18.29 | J8: 0 | K8: 0 | L8: 5.01 | M8: 26.83 | N8: 17.49 | O8: 17.3 | P8: 27.07 | Q8: 25.08 | R8: 26.16 | S8: 29.25 | T8: 25.93 | U8: 0.02 | V8: 0.21 | W8: 0.14 | X8: 0.08 | Y8: 10.71 | Z8: 12.01 | AA8: 9.1 | AB8: 26.83 | AC8: 17.49 | AD8: 17.3 | AE8: 0.069651313 | AF8: 0.072116304 | AG8: 0.082411304 | AH8: 0.077745126 | AI8: 0.044805496 | AJ8: 0.044805496 | AK8: 16.087479 | AL8: 22.424236 | AM8: 22.424236 | AN8: 22.424236 | AO8: 19.061813 | AP8: 19.061813 | AQ8: 19.061813 | AR8: 22.533041 | AS8: 22.144211 | AT8: 0.000143 | AU8: 0.000157 | AV8: 0.000177 | AW8: 0.00017 | AX8: 7.99e-05 | AY8: 7.99e-05 | AZ8: 0.008813737 | BA8: 0.052882424 | BB8: 0.0528824 | BC8: 0.0528824 | BD8: 0.052882424 | BE8: 0.0528824 | BF8: 0.0528824 | BG8: 0.052882424 | BH8: 0.052882424 | BI8: 0.003813423 | BJ8: 0.003663448 | BK8: 0.004384665 | BL8: 0.004120744 | BM8: 0.002634196 | BN8: 0.002634196 | BO8: 0.003298035 | BP8: 0.009894106 | BQ8: 0.0098941 | BR8: 0.0098941 | BS8: 0.009894106 | BT8: 0.0098941 | BU8: 0.0098941 | BV8: 0.009894106 | BW8: 0.009894106
A9: 8 | B9: 0.06 | C9: 0.05 | D9: 0.06 | E9: 0.05 | F9: 0.04 | G9: 0.04 | H9: 67.34 | I9: 18.28 | J9: 0 | K9: 0 | L9: 5.01 | M9: 27.26 | N9: 17.79 | O9: 17.6 | P9: 28.12 | Q9: 26.22 | R9: 27.91 | S9: 29.67 | T9: 25.83 | U9: 0.02 | V9: 0.22 | W9: 0.14 | X9: 0.08 | Y9: 11.18 | Z9: 12.46 | AA9: 9.66 | AB9: 27.26 | AC9: 17.79 | AD9: 17.6 | AE9: 0.059795084 | AF9: 0.061988279 | AG9: 0.071614128 | AH9: 0.066629938 | AI9: 0.03662469 | AJ9: 0.03662469 | AK9: 16.358998 | AL9: 22.802704 | AM9: 22.802704 | AN9: 22.802704 | AO9: 19.383531 | AP9: 19.383531 | AQ9: 19.383531 | AR9: 22.913346 | AS9: 22.517953 | AT9: 0.000109 | AU9: 0.000119 | AV9: 0.000135 | AW9: 0.000128 | AX9: 5.93e-05 | AY9: 5.93e-05 | AZ9: 0.00897365 | BA9: 0.053841899 | BB9: 0.0538419 | BC9: 0.0538419 | BD9: 0.053841899 | BE9: 0.0538419 | BF9: 0.0538419 | BG9: 0.053841899 | BH9: 0.053841899 | BI9: 0.003462148 | BJ9: 0.003336999 | BK9: 0.004064546 | BL9: 0.003759795 | BM9: 0.002252532 | BN9: 0.002252532 | BO9: 0.003410614 | BP9: 0.010231841 | BQ9: 0.0102318 | BR9: 0.0102318 | BS9: 0.010231841 | BT9: 0.0102318 | BU9: 0.0102318 | BV9: 0.010231841 | BW9: 0.010231841
A10: 9 | B10: 0.06 | C10: 0.05 | D10: 0.06 | E10: 0.05 | F10: 0.04 | G10: 0.04 | H10: 74.77 | I10: 18.27 | J10: 0 | K10: 0 | L10: 5 | M10: 27.43 | N10: 17.92 | O10: 17.73 | P10: 29.04 | Q10: 26.97 | R10: 29.09 | S10: 29.84 | T10: 25.92 | U10: 0.02 | V10: 0.22 | W10: 0.14 | X10: 0.08 | Y10: 11.49 | Z10: 12.72 | AA10: 9.95 | AB10: 27.43 | AC10: 17.92 | AD10: 17.73 | AE10: 0.049572655 | AF10: 0.051483651 | AG10: 0.060412369 | AH10: 0.055102224 | AI10: 0.02814722 | AJ10: 0.02814722 | AK10: 16.630516 | AL10: 23.181172 | AM10: 23.181172 | AN10: 23.181172 | AO10: 19.70525 | AP10: 19.70525 | AQ10: 19.70525 | AR10: 23.29365 | AS10: 22.891695 | AT10: 7.37e-05 | AU10: 8.03e-05 | AV10: 9.09e-05 | AW10: 8.51e-05 | AX10: 3.79e-05 | AY10: 3.79e-05 | AZ10: 0.009133434 | BA10: 0.054800607 | BB10: 0.0548006 | BC10: 0.0548006 | BD10: 0.054800607 | BE10: 0.0548006 | BF10: 0.0548006 | BG10: 0.054800607 | BH10: 0.054800607 | BI10: 0.003079089 | BJ10: 0.002980744 | BK10: 0.003713413 | BL10: 0.003365732 | BM10: 0.001839736 | BN10: 0.001839736 | BO10: 0.003523192 | BP10: 0.010569577 | BQ10: 0.0105696 | BR10: 0.0105696 | BS10: 0.010569577 | BT10: 0.0105696 | BU10: 0.0105696 | BV10: 0.010569577 | BW10: 0.010569577
A11: 10 | B11: 0.06 | C11: 0.05 | D11: 0.06 | E11: 0.05 | F11: 0.04 | G11: 0.04 | H11: 81.46 | I11: 18.25 | J11: 0 | K11: 0 | L11: 5 | M11: 27.65 | N11: 18.13 | O11: 17.94 | P11: 29.7 | Q11: 27.32 | R11: 29.66 | S11: 30.15 | T11: 25.71 | U11: 0.02 | V11: 0.22 | W11: 0.15 | X11: 0.08 | Y11: 11.66 | Z11: 12.84 | AA11: 10.06 | AB11: 27.65 | AC11: 18.13 | AD11: 17.94 | AE11: 0.038827464 | AF11: 0.040439358 | AG11: 0.048610017 | AH11: 0.042988643 | AI11: 0.019295282 | AJ11: 0.019295282 | AK11: 16.834155 | AL11: 23.465023 | AM11: 23.465023 | AN11: 23.465023 | AO11: 19.946539 | AP11: 19.946539 | AQ11: 19.946539 | AR11: 23.578879 | AS11: 23.172002 | AT11: 3.69e-05 | AU11: 3.97e-05 | AV11: 4.53e-05 | AW11: 4.03e-05 | AX11: 1.58e-05 | AY11: 1.58e-05 | AZ11: 0.009293347 | BA11: 0.055760082 | BB11: 0.0557601 | BC11: 0.0557601 | BD11: 0.055760082 | BE11: 0.0557601 | BF11: 0.0557601 | BG11: 0.055760082 | BH11: 0.055760082 | BI11: 0.002664247 | BJ11: 0.002594682 | BK11: 0.003331266 | BL11: 0.002938554 | BM11: 0.001395808 | BN11: 0.001395808 | BO11: 0.003635771 | BP11: 0.010907312 | BQ11: 0.0109073 | BR11: 0.0109073 | BS11: 0.010907312 | BT11: 0.0109073 | BU11: 0.0109073 | BV11: 0.010907312 | BW11: 0.010907312
A12: 11 | B12: 0.06 | C12: 0.05 | D12: 0.06 | E12: 0.05 | F12: 0.04 | G12: 0.04 | H12: 85.29 | I12: 18.25 | J12: 0 | K12: 0 | L12: 5 | M12: 27.69 | N12: 18.21 | O12: 18.03 | P12: 30.1 | Q12: 27.43 | R12: 29.84 | S12: 30.25 | T12: 25.73 | U12: 0.02 | V12: 0.21 | W12: 0.14 | X12: 0.08 | Y12: 11.71 | Z12: 12.83 | AA12: 10.02 | AB12: 27.69 | AC12: 18.21 | AD12: 18.03 | AE12: 0.037995779 | AF12: 0.038956439 | AG12: 0.045610629 | AH12: 0.04064978 | AI12: 0.019013858 | AJ12: 0.019013858 | AK12: 17.105674 | AL12: 23.843491 | AM12: 23.843491 | AN12: 23.843491 | AO12: 20.268257 | AP12: 20.268257 | AQ12: 20.268257 | AR12: 23.959183 | AS12: 23.545743 | AT12: 3.48e-05 | AU12: 3.69e-05 | AV12: 4.13e-05 | AW12: 3.69e-05 | AX12: 1.5e-05 | AY12: 1.5e-05 | AZ12: 0.009453259 | BA12: 0.056719557 | BB12: 0.0567196 | BC12: 0.0567196 | BD12: 0.056719557 | BE12: 0.0567196 | BF12: 0.0567196 | BG12: 0.056719557 | BH12: 0.056719557 | BI12: 0.002684271 | BJ12: 0.002576548 | BK12: 0.003204965 | BL12: 0.002852019 | BM12: 0.001411075 | BN12: 0.001411075 | BO12: 0.00374707 | BP12: 0.011241209 | BQ12: 0.0112412 | BR12: 0.0112412 | BS12: 0.011241209 | BT12: 0.0112412 | BU12: 0.0112412 | BV12: 0.011241209 | BW12: 0.011241209
A13: 12 | B13: 0.06 | C13: 0.05 | D13: 0.06 | E13: 0.05 | F13: 0.04 | G13: 0.04 | H13: 87.17 | I13: 18.24 | J13: 0 | K13: 0 | L13: 4.99 | M13: 27.91 | N13: 18.38 | O13: 18.21 | P13: 30.32 | Q13: 27.46 | R13: 29.89 | S13: 30.47 | T13: 25.65 | U13: 0.02 | V13: 0.22 | W13: 0.14 | X13: 0.08 | Y13: 11.68 | Z13: 12.75 | AA13: 9.87 | AB13: 27.91 | AC13: 18.38 | AD13: 18.21 | AE13: 0.037117811 | AF13: 0.037405737 | AG13: 0.042491133 | AH13: 0.038214655 | AI13: 0.01871362 | AJ13: 0.01871362 | AK13: 17.377192 | AL13: 24.221959 | AM13: 24.221959 | AN13: 24.221959 | AO13: 20.589975 | AP13: 20.589975 | AQ13: 20.589975 | AR13: 24.339488 | AS13: 23.919485 | AT13: 3.25e-05 | AU13: 3.4e-05 | AV13: 3.72e-05 | AW13: 3.35e-05 | AX13: 1.41e-05 | AY13: 1.41e-05 | AZ13: 0.009613172 | BA13: 0.057679032 | BB13: 0.057679 | BC13: 0.057679 | BD13: 0.057679032 | BE13: 0.057679 | BF13: 0.057679 | BG13: 0.057679032 | BH13: 0.057679032 | BI13: 0.002701535 | BJ13: 0.002553465 | BK13: 0.003066119 | BL13: 0.002755913 | BM13: 0.001425183 | BN13: 0.001425183 | BO13: 0.003859648 | BP13: 0.011578944 | BQ13: 0.0115789 | BR13: 0.0115789 | BS13: 0.011578944 | BT13: 0.0115789 | BU13: 0.0115789 | BV13: 0.011578944 | BW13: 0.011578944
... A51: 50 | B51: 0.08 | C51: 0.06 | D51: 0.08 | E51: 0.06 | F51: 0.05 | G51: 0.05 | H51: 81.71 | I51: 17.1 | J51: 0 | K51: 0 | L51: 4.68 | M51: 31.29 | N51: 20.55 | O51: 20.34 | P51: 33.23 | Q51: 29.95 | R51: 33.93 | S51: 33.13 | T51: 23.79 | U51: 0.02 | V51: 0.25 | W51: 0.17 | X51: 0.09 | Y51: 12.35 | Z51: 12.92 | AA51: 9.61 | AB51: 31.29 | AC51: 20.55 | AD51: 20.34 | AE51: 0.026914777 | AF51: 0.025706768 | AG51: 0.033554617 | AH51: 0.029965821 | AI51: 0.01417027 | AJ51: 0.01417027 | AK51: 20.906935 | AL51: 29.142045 | AM51: 29.142045 | AN51: 29.142045 | AO51: 24.772314 | AP51: 24.772314 | AQ51: 24.772314 | AR51: 29.283446 | AS51: 28.778131 | AT51: 1.81e-05 | AU51: 1.75e-05 | AV51: 2.32e-05 | AW51: 2.09e-05 | AX51: 9.21e-06 | AY51: 9.21e-06 | AZ51: 0.011896978 | BA51: 0.07138187 | BB51: 0.0713819 | BC51: 0.0713819 | BD51: 0.07138187 | BE51: 0.0713819 | BF51: 0.0713819 | BG51: 0.07138187 | BH51: 0.07138187 | BI51: 0.002480229 | BJ51: 0.002249242 | BK51: 0.003045056 | BL51: 0.00271828 | BM51: 0.001314623 | BN51: 0.001314623 | BO51: 0.005412718 | BP51: 0.016238155 | BQ51: 0.0162382 | BR51: 0.0162382 | BS51: 0.016238155 | BT51: 0.0162382 | BU51: 0.0162382 | BV51: 0.016238155 | BW51: 0.016238155

Sheet Input
S1: Electricity | T1: Electricity | U1: Electricity | V1: Natural_gas | W1: Natural_gas | X1: Natural_gas | Y1: Heating Oil | Z1: Heating Oil | AA1: Heating Oil
S2: Retail_Prices | T2: Retail_Prices | U2: Retail_Prices | V2: Retail_Prices | W2: Retail_Prices | X2: Retail_Prices | Y2: Retail_Prices | Z2: Retail_Prices | AA2: Retail_Prices
A3: Study Year | B3: Summer_On-Peak | C3: Summer_Off-Peak | D3: Winter_On-Peak | E3: Winter_Off-Peak | F3: Shoulder_On-Peak | G3: Summer_Gener_Capacity | H3: Summer_TD | I3: Natural_Gas | J3: Res_Fuel_Oil | K3: Com_Fuel_Oil | L3: Ind_Fuel_Oil | M3: Res_Propane | N3: Com_Propane | O3: Ind_Propane | P3: Diesel_Transportation | Q3: Gasoline_Transportation | R3: =Originial!AE16 -> Water | S3: =Originial!AO16 -> Res | T3: =Originial!AP16 -> Commercial | U3: =Originial!AQ16 -> Industrial | V3: =Originial!AT16 -> Res | W3: =Originial!AU16 -> Commercial | X3: =Originial!AV16 -> Industrial | Y3: =Originial!AY16 -> Res | Z3: =Originial!AZ16 -> Commercial | AA3: =Originial!BA16 -> Industrial | AB3: Summer_On-Peak | AC3: Summer_Off-Peak | AD3: Winter_On-Peak | AE3: Winter_Off-Peak | AF3: Shoulder_On-Peak | AG3: Natural_Gas | AH3: Res_Fuel_Oil | AI3: Com_Fuel_Oil | AJ3: Ind_Fuel_Oil | AK3: Res_Propane | AL3: Com_Propane | AM3: Ind_Propane | AN3: Diesel_Transportation | AO3: Gasoline_Transportation | AP3: Summer_On-Peak | AQ3: Summer_Off-Peak | AR3: Winter_On-Peak | AS3: Winter_Off-Peak | AT3: Shoulder_On-Peak | AU3: Natural_Gas | AV3: Res_Fuel_Oil | AW3: Com_Fuel_Oil | AX3: Ind_Fuel_Oil | AY3: Res_Propane | AZ3: Com_Propane | BA3: Ind_Propane | BB3: Diesel_Transportation | BC3: Gasoline_Transportation | BD3: Summer_On-Peak | BE3: Summer_Off-Peak | BF3: Winter_On-Peak | BG3: Winter_Off-Peak | BH3: Shoulder_On-Peak | BI3: Natural_Gas | BJ3: Res_Fuel_Oil | BK3: Com_Fuel_Oil | BL3: Ind_Fuel_Oil | BM3: Res_Propane | BN3: Com_Propane | BO3: Ind_Propane | BP3: Diesel_Transportation | BQ3: Gasoline_Transportation
A4: Unit | B4: =Originial!B19 -> $/kWh | C4: =Originial!C19 -> $/kWh | D4: =Originial!D19 -> $/kWh | E4: =Originial!E19 -> $/kWh | F4: =Originial!F19 -> $/kWh | G4: =Originial!H19 -> $/kW-yr | H4: =Originial!J19 -> $/kW-yr | I4: =Originial!N19 -> $/MMBtu | J4: =Originial!O19 -> $/MMBtu | K4: =Originial!P19 -> $/MMBtu | L4: =Originial!Q19 -> $/MMBtu | M4: =Originial!R19 -> $/MMBtu | N4: =Originial!S19 -> $/MMBtu | O4: =Originial!T19 -> $/MMBtu | P4: =Originial!U19 -> $/MMBtu | Q4: =Originial!V19 -> $/MMBtu | R4: =Originial!AE19 -> $/Gallon | S4: =Originial!AO19 -> $/kWh | T4: =Originial!AP19 -> $/kWh | U4: =Originial!AQ19 -> $/kWh | V4: =Originial!AT19 -> $/MMBtu | W4: =Originial!AU19 -> $/MMBtu | X4: =Originial!AV19 -> $/MMBtu | Y4: =Originial!AY19 -> $/MMBtu | Z4: =Originial!AZ19 -> $/MMBtu | AA4: =Originial!BA19 -> $/MMBtu | AB4: Carbon | AC4: Carbon | AD4: Carbon | AE4: Carbon | AF4: Carbon | AG4: Carbon | AH4: Carbon | AI4: Carbon | AJ4: Carbon | AK4: Carbon | AL4: Carbon | AM4: Carbon | AN4: Carbon | AO4: Carbon | AP4: N2O | AQ4: N2O | AR4: N2O | AS4: N2O | AT4: N2O | AU4: N2O | AV4: N2O | AW4: N2O | AX4: N2O | AY4: N2O | AZ4: N2O | BA4: N2O | BB4: N2O | BC4: N2O | BD4: CH4 | BE4: CH4 | BF4: CH4 | BG4: CH4 | BH4: CH4 | BI4: CH4 | BJ4: CH4 | BK4: CH4 | BL4: CH4 | BM4: CH4 | BN4: CH4 | BO4: CH4 | BP4: CH4 | BQ4: CH4 | BR4: Double check the units with Matt
A5: Clean Unit | B5: usdperkWh | C5: usdperkWh | D5: usdperkWh | E5: usdperkWh | F5: usdperkWh | G5: usdperkW-yr | H5: usdperkW-yr | I5: usdperMMBtu | J5: usdperMMBtu | K5: usdperMMBtu | L5: usdperMMBtu | M5: usdperMMBtu | N5: usdperMMBtu | O5: usdperMMBtu | P5: usdperMMBtu | Q5: usdperMMBtu | R5: usdpergallon | S5: usdperkWh | T5: usdperkWh | U5: usdperkWh | V5: usdperMMBtu | W5: usdperMMBtu | X5: usdperMMBtu | Y5: usdperMMBtu | Z5: usdperMMBtu | AA5: usdperMMBtu | AB5: usdperMMBtu | AC5: usdperMMBtu | AD5: usdperMMBtu | AE5: usdperMMBtu | AF5: usdperMMBtu | AG5: usdperMMBtu | AH5: usdperMMBtu | AI5: usdperMMBtu | AJ5: usdperMMBtu | AK5: usdperMMBtu | AL5: usdperMMBtu | AM5: usdperMMBtu | AN5: usdperMMBtu | AO5: usdperMMBtu | AP5: usdperMMBtu | AQ5: usdperMMBtu | AR5: usdperMMBtu | AS5: usdperMMBtu | AT5: usdperMMBtu | AU5: usdperMMBtu | AV5: usdperMMBtu | AW5: usdperMMBtu | AX5: usdperMMBtu | AY5: usdperMMBtu | AZ5: usdperMMBtu | BA5: usdperMMBtu | BB5: usdperMMBtu | BC5: usdperMMBtu | BD5: usdperMMBtu | BE5: usdperMMBtu | BF5: usdperMMBtu | BG5: usdperMMBtu | BH5: usdperMMBtu | BI5: usdperMMBtu | BJ5: usdperMMBtu | BK5: usdperMMBtu | BL5: usdperMMBtu | BM5: usdperMMBtu | BN5: usdperMMBtu | BO5: usdperMMBtu | BP5: usdperMMBtu | BQ5: usdperMMBtu
A6: study year_unit | B6: summer on-peak_$/kwh | C6: summer off-peak_$/kwh | D6: winter on-peak_$/kwh | E6: winter off-peak_$/kwh | F6: shoulder_$/kwh | G6: summer gener. capacity_$/kw-yr | H6: summer t&d_$/kw-yr | I6: natural gas_$/mmbtu | J6: res fuel oil_$/mmbtu | K6: com fuel oil_$/mmbtu | L6: ind fuel oil_$/mmbtu | M6: res propane_$/mmbtu | N6: com propane_$/mmbtu | O6: ind propane_$/mmbtu | P6: diesel, transportation_$/mmbtu | Q6: gasoline, transportation_$/mmbtu | R6: water_$/gallon | S6: res_$/kwh | T6: commercial_$/kwh | U6: industrial_$/kwh | V6: res_$/mmbtu | W6: commercial_$/mmbtu | X6: industrial_$/mmbtu | Y6: res_$/mmbtu | Z6: commercial_$/mmbtu | AA6: industrial_$/mmbtu | AB6: summer on-peak_carbon | AC6: summer off-peak_carbon | AD6: winter on-peak_carbon | AE6: winter off-peak_carbon | AF6: shoulder on-peak_carbon | AG6: natural gas_carbon | AH6: res fuel oil_carbon | AI6: com fuel oil_carbon | AJ6: ind fuel oil_carbon | AK6: res propane_carbon | AL6: com propane_carbon | AM6: ind propane_carbon | AN6: diesel, transportation_carbon | AO6: gasoline, transportation_carbon | AP6: summer on-peak_n2o | AQ6: summer off-peak_n2o | AR6: winter on-peak_n2o | AS6: winter off-peak_n2o | AT6: shoulder on-peak_n2o | AU6: natural gas_n2o | AV6: res fuel oil_n2o | AW6: com fuel oil_n2o | AX6: ind fuel oil_n2o | AY6: res propane_n2o | AZ6: com propane_n2o | BA6: ind propane_n2o | BB6: diesel, transportation_n2o | BC6: gasoline, transportation_n2o | BD6: summer on-peak_ch4 | BE6: summer off-peak_ch4 | BF6: winter on-peak_ch4 | BG6: winter off-peak_ch4 | BH6: shoulder on-peak_ch4 | BI6: natural gas_ch4 | BJ6: res fuel oil_ch4 | BK6: com fuel oil_ch4 | BL6: ind fuel oil_ch4 | BM6: res propane_ch4 | BN6: com propane_ch4 | BO6: ind propane_ch4 | BP6: diesel, transportation_ch4 | BQ6: gasoline, transportation_ch4
B7: =_xlfn.CONCAT(LOWER(B3),"_",B5) -> summer_on-peak_usdperkWh | C7: =_xlfn.CONCAT(LOWER(C3),"_",C5) -> summer_off-peak_usdperkWh | D7: =_xlfn.CONCAT(LOWER(D3),"_",D5) -> winter_on-peak_usdperkWh | E7: =_xlfn.CONCAT(LOWER(E3),"_",E5) -> winter_off-peak_usdperkWh | F7: =_xlfn.CONCAT(LOWER(F3),"_",F5) -> shoulder_on-peak_usdperkWh | G7: =_xlfn.CONCAT(LOWER(G3),"_",G5) -> summer_gener_capacity_usdperkW-yr | H7: =_xlfn.CONCAT(LOWER(H3),"_",H5) -> summer_td_usdperkW-yr | I7: =_xlfn.CONCAT(LOWER(I3),"_",I5) -> natural_gas_usdperMMBtu | ... R7: =_xlfn.CONCAT(LOWER(R3),"_",R5) -> water_usdpergallon | S7: =_xlfn.CONCAT(S1,"_",S2,"_",LOWER(S3),"_",S5) -> Electricity_Retail_Prices_res_usdperkWh | T7: =_xlfn.CONCAT(T1,"_",T2,"_",LOWER(T3),"_",T5) -> Electricity_Retail_Prices_commercial_usdperkWh | U7: =_xlfn.CONCAT(U1,"_",U2,"_",LOWER(U3),"_",U5) -> Electricity_Retail_Prices_industrial_usdperkWh | V7: =_xlfn.CONCAT(V1,"_",V2,"_",LOWER(V3),"_",V5) -> Natural_gas_Retail_Prices_res_usdperMMBtu | W7: =_xlfn.CONCAT(W1,"_",W2,"_",LOWER(W3),"_",W5) -> Natural_gas_Retail_Prices_commercial_usdperMMBtu | X7: =_xlfn.CONCAT(X1,"_",X2,"_",LOWER(X3),"_",X5) -> Natural_gas_Retail_Prices_industrial_usdperMMBtu | Y7: =_xlfn.CONCAT(Y1,"_",Y2,"_",LOWER(Y3),"_",Y5) -> Heating Oil_Retail_Prices_res_usdperMMBtu | Z7: =_xlfn.CONCAT(Z1,"_",Z2,"_",LOWER(Z3),"_",Z5) -> Heating Oil_Retail_Prices_commercial_usdperMMBtu | AA7: =_xlfn.CONCAT(AA1,"_",AA2,"_",LOWER(AA3),"_",AA5) -> Heating Oil_Retail_Prices_industrial_usdperMMBtu | AB7: =_xlfn.CONCAT(LOWER(AB3),"_",AB5,"_",LOWER(AB4)) -> summer_on-peak_usdperMMBtu_carbon | AC7: =_xlfn.CONCAT(LOWER(AC3),"_",AC5,"_",LOWER(AC4)) -> summer_off-peak_usdperMMBtu_carbon | AD7: =_xlfn.CONCAT(LOWER(AD3),"_",AD5,"_",LOWER(AD4)) -> winter_on-peak_usdperMMBtu_carbon | AE7: =_xlfn.CONCAT(LOWER(AE3),"_",AE5,"_",LOWER(AE4)) -> winter_off-peak_usdperMMBtu_carbon | AF7: =_xlfn.CONCAT(LOWER(AF3),"_",AF5,"_",LOWER(AF4)) -> shoulder_on-peak_usdperMMBtu_carbon | AG7: =_xlfn.CONCAT(LOWER(AG3),"_",AG5,"_",LOWER(AG4)) -> natural_gas_usdperMMBtu_carbon | AH7: =_xlfn.CONCAT(LOWER(AH3),"_",AH5,"_",LOWER(AH4)) -> res_fuel_oil_usdperMMBtu_carbon | AI7: =_xlfn.CONCAT(LOWER(AI3),"_",AI5,"_",LOWER(AI4)) -> com_fuel_oil_usdperMMBtu_carbon | ... BQ7: =_xlfn.CONCAT(LOWER(BQ3),"_",BQ5,"_",LOWER(BQ4)) -> gasoline_transportation_usdperMMBtu_ch4
B8: summer_on-peak_usdperkWh | C8: summer_off-peak_usdperkWh | D8: winter_on-peak_usdperkWh | E8: winter_off-peak_usdperkWh | F8: shoulder_on-peak_usdperkWh | G8: summer_gener_capacity_usdperkW-yr | H8: summer_td_usdperkW-yr | I8: natural_gas_usdperMMBtu | J8: res_fuel_oil_usdperMMBtu | K8: com_fuel_oil_usdperMMBtu | L8: ind_fuel_oil_usdperMMBtu | M8: res_propane_usdperMMBtu | N8: com_propane_usdperMMBtu | O8: ind_propane_usdperMMBtu | P8: diesel_transportation_usdperMMBtu | Q8: gasoline_transportation_usdperMMBtu | R8: water_usdpergallon | S8: =S7 -> Electricity_Retail_Prices_res_usdperkWh | T8: =T7 -> Electricity_Retail_Prices_commercial_usdperkWh | U8: =U7 -> Electricity_Retail_Prices_industrial_usdperkWh | V8: =V7 -> Natural_gas_Retail_Prices_res_usdperMMBtu | W8: =W7 -> Natural_gas_Retail_Prices_commercial_usdperMMBtu | X8: =X7 -> Natural_gas_Retail_Prices_industrial_usdperMMBtu | Y8: =Y7 -> Heating Oil_Retail_Prices_res_usdperMMBtu | Z8: =Z7 -> Heating Oil_Retail_Prices_commercial_usdperMMBtu | AA8: =AA7 -> Heating Oil_Retail_Prices_industrial_usdperMMBtu | AB8: summer_on-peak_usdperMMBtu_carbon | AC8: summer_off-peak_usdperMMBtu_carbon | AD8: winter_on-peak_usdperMMBtu_carbon | AE8: winter_off-peak_usdperMMBtu_carbon | AF8: shoulder_on-peak_usdperMMBtu_carbon | AG8: natural_gas_usdperMMBtu_carbon | AH8: res_fuel_oil_usdperMMBtu_carbon | AI8: com_fuel_oil_usdperMMBtu_carbon | AJ8: ind_fuel_oil_usdperMMBtu_carbon | AK8: res_propane_usdperMMBtu_carbon | AL8: com_propane_usdperMMBtu_carbon | AM8: ind_propane_usdperMMBtu_carbon | AN8: diesel_transportation_usdperMMBtu_carbon | AO8: gasoline_transportation_usdperMMBtu_carbon | AP8: summer_on-peak_usdperMMBtu_n2o | AQ8: summer_off-peak_usdperMMBtu_n2o | AR8: winter_on-peak_usdperMMBtu_n2o | AS8: winter_off-peak_usdperMMBtu_n2o | AT8: shoulder_on-peak_usdperMMBtu_n2o | AU8: natural_gas_usdperMMBtu_n2o | AV8: res_fuel_oil_usdperMMBtu_n2o | AW8: com_fuel_oil_usdperMMBtu_n2o | AX8: ind_fuel_oil_usdperMMBtu_n2o | AY8: res_propane_usdperMMBtu_n2o | AZ8: com_propane_usdperMMBtu_n2o | BA8: ind_propane_usdperMMBtu_n2o | BB8: diesel_transportation_usdperMMBtu_n2o | BC8: gasoline_transportation_usdperMMBtu_n2o | BD8: summer_on-peak_usdperMMBtu_ch4 | BE8: summer_off-peak_usdperMMBtu_ch4 | BF8: winter_on-peak_usdperMMBtu_ch4 | BG8: winter_off-peak_usdperMMBtu_ch4 | BH8: shoulder_on-peak_usdperMMBtu_ch4 | BI8: natural_gas_usdperMMBtu_ch4 | BJ8: res_fuel_oil_usdperMMBtu_ch4 | BK8: com_fuel_oil_usdperMMBtu_ch4 | BL8: ind_fuel_oil_usdperMMBtu_ch4 | BM8: res_propane_usdperMMBtu_ch4 | BN8: com_propane_usdperMMBtu_ch4 | BO8: ind_propane_usdperMMBtu_ch4 | BP8: diesel_transportation_usdperMMBtu_ch4 | BQ8: gasoline_transportation_usdperMMBtu_ch4
A9: 1 | B9: =Originial!B20 -> 0.06 | C9: =Originial!C20 -> 0.04 | D9: =Originial!D20 -> 0.06 | E9: =Originial!E20 -> 0.04 | F9: =Originial!F20 -> 0.04 | G9: =Originial!H20 -> 89.69 | H9: =Originial!J20 -> 18.6 | I9: =Originial!N20 -> 5.62 | J9: =Originial!O20 -> 24.68 | K9: =Originial!P20 -> 18.71 | L9: =Originial!Q20 -> 18.71 | M9: =Originial!R20 -> 25.38 | N9: =Originial!S20 -> 22.83 | O9: =Originial!T20 -> 22.83 | P9: =Originial!U20 -> 28.12 | Q9: =Originial!V20 -> 27.09 | R9: =Originial!AE20 -> 0.017 | S9: =Originial!AO20 -> 0.2 | T9: =Originial!AP20 -> 0.14 | U9: =Originial!AQ20 -> 0.08 | V9: =Originial!AT20 -> 11.26 | W9: =Originial!AU20 -> 9.77 | X9: =Originial!AV20 -> 7.91 | Y9: =Originial!AY20 -> 24.68 | Z9: =Originial!AZ20 -> 18.71 | AA9: =Originial!BA20 -> 18.71 | AB9: =GHG!B25 -> 0.077749014 | AC9: =GHG!C25 -> 0.075741179 | AD9: =GHG!D25 -> 0.084995875 | AE9: =GHG!E25 -> 0.08228085 | AF9: =GHG!F25 -> 0.05206803 | AG9: =GHG!AB25 -> 14.594126 | AH9: =GHG!AC25 -> 20.342661 | AI9: =GHG!AD25 -> 20.342661 | AJ9: =GHG!AE25 -> 20.342661 | AK9: =GHG!AF25 -> 17.292362 | AL9: =GHG!AG25 -> 17.292362 | AM9: =GHG!AH25 -> 17.292362 | AN9: =GHG!AI25 -> 20.441367 | AO9: =GHG!AJ25 -> 20.08863 | AP9: =GHG!B25 -> 0.077749014 | AQ9: =GHG!C25 -> 0.075741179 | AR9: =GHG!D25 -> 0.084995875 | AS9: =GHG!E25 -> 0.08228085 | AT9: =GHG!F25 -> 0.05206803 | AU9: =GHG!AB89 -> 0.007866672 | AV9: =GHG!AC89 -> 0.047200029 | AW9: =GHG!AD89 -> 0.0472 | AX9: =GHG!AE89 -> 0.0472 | AY9: =GHG!AF89 -> 0.047200029 | AZ9: =GHG!AG89 -> 0.0472 | BA9: =GHG!AH89 -> 0.0472 | BB9: =GHG!AI89 -> 0.047200029 | BC9: =GHG!AJ89 -> 0.047200029 | BD9: =GHG!B153 -> 0.004387404 | BE9: =GHG!C153 -> 0.003927791 | BF9: =GHG!D153 -> 0.004432337 | BG9: =GHG!E153 -> 0.004162093 | BH9: =GHG!F153 -> 0.003112023 | BI9: =GHG!AB153 -> 0.002687809 | BJ9: =GHG!AC153 -> 0.008063428 | BK9: =GHG!AD153 -> 0.0080634 | BL9: =GHG!AE153 -> 0.0080634 | BM9: =GHG!AF153 -> 0.008063428 | BN9: =GHG!AG153 -> 0.0080634 | BO9: =GHG!AH153 -> 0.0080634 | BP9: =GHG!AI153 -> 0.008063428 | BQ9: =GHG!AJ153 -> 0.008063428
A10: 2 | B10: =Originial!B21 -> 0.06 | C10: =Originial!C21 -> 0.05 | D10: =Originial!D21 -> 0.06 | E10: =Originial!E21 -> 0.05 | F10: =Originial!F21 -> 0.04 | G10: =Originial!H21 -> 49.6 | H10: =Originial!J21 -> 18.32 | I10: =Originial!N21 -> 4.73 | J10: =Originial!O21 -> 25 | K10: =Originial!P21 -> 18.24 | L10: =Originial!Q21 -> 18.19 | M10: =Originial!R21 -> 25.19 | N10: =Originial!S21 -> 22.61 | O10: =Originial!T21 -> 22.51 | P10: =Originial!U21 -> 28.19 | Q10: =Originial!V21 -> 26.53 | R10: =Originial!AE21 -> 0.017 | S10: =Originial!AO21 -> 0.21 | T10: =Originial!AP21 -> 0.14 | U10: =Originial!AQ21 -> 0.08 | V10: =Originial!AT21 -> 10.72 | W10: =Originial!AU21 -> 9.96 | X10: =Originial!AV21 -> 7.69 | Y10: =Originial!AY21 -> 25 | Z10: =Originial!AZ21 -> 18.24 | AA10: =Originial!BA21 -> 18.19 | AB10: =GHG!B26 -> 0.080499329 | AC10: =GHG!C26 -> 0.079677276 | AD10: =GHG!D26 -> 0.089508689 | AE10: =GHG!E26 -> 0.086465299 | AF10: =GHG!F26 -> 0.054188785 | AG10: =GHG!AB26 -> 14.865645 | AH10: =GHG!AC26 -> 20.721129 | AI10: =GHG!AD26 -> 20.721129 | AJ10: =GHG!AE26 -> 20.721129 | AK10: =GHG!AF26 -> 17.61408 | AL10: =GHG!AG26 -> 17.61408 | AM10: =GHG!AH26 -> 17.61408 | AN10: =GHG!AI26 -> 20.821671 | AO10: =GHG!AJ26 -> 20.462372 | AP10: =GHG!B26 -> 0.080499329 | AQ10: =GHG!C26 -> 0.079677276 | AR10: =GHG!D26 -> 0.089508689 | AS10: =GHG!E26 -> 0.086465299 | AT10: =GHG!F26 -> 0.054188785 | AU10: =GHG!AB90 -> 0.008023514 | AV10: =GHG!AC90 -> 0.048141082 | AW10: =GHG!AD90 -> 0.0481411 | AX10: =GHG!AE90 -> 0.0481411 | AY10: =GHG!AF90 -> 0.048141082 | AZ10: =GHG!AG90 -> 0.0481411 | BA10: =GHG!AH90 -> 0.0481411 | BB10: =GHG!AI90 -> 0.048141082 | BC10: =GHG!AJ90 -> 0.048141082 | BD10: =GHG!B154 -> 0.004409191 | BE10: =GHG!C154 -> 0.004008308 | BF10: =GHG!D154 -> 0.004559877 | BG10: =GHG!E154 -> 0.004307253 | BH10: =GHG!F154 -> 0.003165647 | BI10: =GHG!AB154 -> 0.002783757 | BJ10: =GHG!AC154 -> 0.00835127 | BK10: =GHG!AD154 -> 0.0083513 | BL10: =GHG!AE154 -> 0.0083513 | BM10: =GHG!AF154 -> 0.00835127 | BN10: =GHG!AG154 -> 0.0083513 | BO10: =GHG!AH154 -> 0.0083513 | BP10: =GHG!AI154 -> 0.00835127 | BQ10: =GHG!AJ154 -> 0.00835127
A11: 3 | B11: =Originial!B22 -> 0.06 | C11: =Originial!C22 -> 0.05 | D11: =Originial!D22 -> 0.06 | E11: =Originial!E22 -> 0.05 | F11: =Originial!F22 -> 0.04 | G11: =Originial!H22 -> 42.36 | H11: =Originial!J22 -> 18.31 | I11: =Originial!N22 -> 4.71 | J11: =Originial!O22 -> 25.57 | K11: =Originial!P22 -> 17.97 | L11: =Originial!Q22 -> 17.87 | M11: =Originial!R22 -> 25.19 | N11: =Originial!S22 -> 22.75 | O11: =Originial!T22 -> 22.7 | P11: =Originial!U22 -> 28.53 | Q11: =Originial!V22 -> 26.25 | R11: =Originial!AE22 -> 0.017 | S11: =Originial!AO22 -> 0.21 | T11: =Originial!AP22 -> 0.14 | U11: =Originial!AQ22 -> 0.08 | V11: =Originial!AT22 -> 10.38 | W11: =Originial!AU22 -> 10.34 | X11: =Originial!AV22 -> 7.76 | Y11: =Originial!AY22 -> 25.57 | Z11: =Originial!AZ22 -> 17.97 | AA11: =Originial!BA22 -> 17.87 | AB11: =GHG!B27 -> 0.083297273 | AC11: =GHG!C27 -> 0.083705682 | AD11: =GHG!D27 -> 0.09412859 | AE11: =GHG!E27 -> 0.090746684 | AF11: =GHG!F27 -> 0.056351623 | AG11: =GHG!AB27 -> 15.137164 | AH11: =GHG!AC27 -> 21.099597 | AI11: =GHG!AD27 -> 21.099597 | AJ11: =GHG!AE27 -> 21.099597 | AK11: =GHG!AF27 -> 17.935799 | AL11: =GHG!AG27 -> 17.935799 | AM11: =GHG!AH27 -> 17.935799 | AN11: =GHG!AI27 -> 21.201976 | AO11: =GHG!AJ27 -> 20.836114 | AP11: =GHG!B27 -> 0.083297273 | AQ11: =GHG!C27 -> 0.083705682 | AR11: =GHG!D27 -> 0.09412859 | AS11: =GHG!E27 -> 0.090746684 | AT11: =GHG!F27 -> 0.056351623 | AU11: =GHG!AB91 -> 0.008180356 | AV11: =GHG!AC91 -> 0.049082136 | AW11: =GHG!AD91 -> 0.0490821 | AX11: =GHG!AE91 -> 0.0490821 | AY11: =GHG!AF91 -> 0.049082136 | AZ11: =GHG!AG91 -> 0.0490821 | BA11: =GHG!AH91 -> 0.0490821 | BB11: =GHG!AI91 -> 0.049082136 | BC11: =GHG!AJ91 -> 0.049082136 | BD11: =GHG!B155 -> 0.004423647 | BE11: =GHG!C155 -> 0.004086524 | BF11: =GHG!D155 -> 0.004687384 | BG11: =GHG!E155 -> 0.004454156 | BH11: =GHG!F155 -> 0.003216739 | BI11: =GHG!AB155 -> 0.002880984 | BJ11: =GHG!AC155 -> 0.008642951 | BK11: =GHG!AD155 -> 0.008643 | BL11: =GHG!AE155 -> 0.008643 | BM11: =GHG!AF155 -> 0.008642951 | BN11: =GHG!AG155 -> 0.008643 | BO11: =GHG!AH155 -> 0.008643 | BP11: =GHG!AI155 -> 0.008642951 | BQ11: =GHG!AJ155 -> 0.008642951
A12: 4 | B12: =Originial!B23 -> 0.06 | C12: =Originial!C23 -> 0.05 | D12: =Originial!D23 -> 0.06 | E12: =Originial!E23 -> 0.05 | F12: =Originial!F23 -> 0.04 | G12: =Originial!H23 -> 63.21 | H12: =Originial!J23 -> 18.3 | I12: =Originial!N23 -> 4.59 | J12: =Originial!O23 -> 26.19 | K12: =Originial!P23 -> 17.72 | L12: =Originial!Q23 -> 17.57 | M12: =Originial!R23 -> 25.4 | N12: =Originial!S23 -> 23.11 | O12: =Originial!T23 -> 23.23 | P12: =Originial!U23 -> 28.89 | Q12: =Originial!V23 -> 25.94 | R12: =Originial!AE23 -> 0.017 | S12: =Originial!AO23 -> 0.22 | T12: =Originial!AP23 -> 0.14 | U12: =Originial!AQ23 -> 0.08 | V12: =Originial!AT23 -> 10.19 | W12: =Originial!AU23 -> 10.84 | X12: =Originial!AV23 -> 7.94 | Y12: =Originial!AY23 -> 26.19 | Z12: =Originial!AZ23 -> 17.72 | AA12: =Originial!BA23 -> 17.57 | AB12: =GHG!B28 -> 0.085763361 | AC12: =GHG!C28 -> 0.087439496 | AD12: =GHG!D28 -> 0.09842009 | AE12: =GHG!E28 -> 0.094705953 | AF12: =GHG!F28 -> 0.058298587 | AG12: =GHG!AB28 -> 15.340803 | AH12: =GHG!AC28 -> 21.383448 | AI12: =GHG!AD28 -> 21.383448 | AJ12: =GHG!AE28 -> 21.383448 | AK12: =GHG!AF28 -> 18.177088 | AL12: =GHG!AG28 -> 18.177088 | AM12: =GHG!AH28 -> 18.177088 | AN12: =GHG!AI28 -> 21.487204 | AO12: =GHG!AJ28 -> 21.116421 | AP12: =GHG!B28 -> 0.085763361 | AQ12: =GHG!C28 -> 0.087439496 | AR12: =GHG!D28 -> 0.09842009 | AS12: =GHG!E28 -> 0.094705953 | AT12: =GHG!F28 -> 0.058298587 | AU12: =GHG!AB92 -> 0.00833707 | AV12: =GHG!AC92 -> 0.050022421 | AW12: =GHG!AD92 -> 0.0500224 | AX12: =GHG!AE92 -> 0.0500224 | AY12: =GHG!AF92 -> 0.050022421 | AZ12: =GHG!AG92 -> 0.0500224 | BA12: =GHG!AH92 -> 0.0500224 | BB12: =GHG!AI92 -> 0.050022421 | BC12: =GHG!AJ92 -> 0.050022421 | BD12: =GHG!B156 -> 0.004426783 | BE12: =GHG!C156 -> 0.004158783 | BF12: =GHG!D156 -> 0.00481068 | BG12: =GHG!E156 -> 0.004598845 | BH12: =GHG!F156 -> 0.003262414 | BI12: =GHG!AB156 -> 0.002976931 | BJ12: =GHG!AC156 -> 0.008930793 | BK12: =GHG!AD156 -> 0.0089308 | BL12: =GHG!AE156 -> 0.0089308 | BM12: =GHG!AF156 -> 0.008930793 | BN12: =GHG!AG156 -> 0.0089308 | BO12: =GHG!AH156 -> 0.0089308 | BP12: =GHG!AI156 -> 0.008930793 | BQ12: =GHG!AJ156 -> 0.008930793
A13: 5 | B13: =Originial!B24 -> 0.07 | C13: =Originial!C24 -> 0.05 | D13: =Originial!D24 -> 0.07 | E13: =Originial!E24 -> 0.05 | F13: =Originial!F24 -> 0.04 | G13: =Originial!H24 -> 57.55 | H13: =Originial!J24 -> 18.29 | I13: =Originial!N24 -> 5.02 | J13: =Originial!O24 -> 26.88 | K13: =Originial!P24 -> 17.5 | L13: =Originial!Q24 -> 17.3 | M13: =Originial!R24 -> 25.8 | N13: =Originial!S24 -> 23.63 | O13: =Originial!T24 -> 23.99 | P13: =Originial!U24 -> 29.3 | Q13: =Originial!V24 -> 26 | R13: =Originial!AE24 -> 0.017 | S13: =Originial!AO24 -> 0.22 | T13: =Originial!AP24 -> 0.15 | U13: =Originial!AQ24 -> 0.08 | V13: =Originial!AT24 -> 9.98 | W13: =Originial!AU24 -> 11.31 | X13: =Originial!AV24 -> 8.15 | Y13: =Originial!AY24 -> 26.88 | Z13: =Originial!AZ24 -> 17.5 | AA13: =Originial!BA24 -> 17.3 | AB13: =GHG!B29 -> 0.088650607 | AC13: =GHG!C29 -> 0.091640981 | AD13: =GHG!D29 -> 0.10324078 | AE13: =GHG!E29 -> 0.099169094 | AF13: =GHG!F29 -> 0.060540333 | AG13: =GHG!AB29 -> 15.612321 | AH13: =GHG!AC29 -> 21.761916 | AI13: =GHG!AD29 -> 21.761916 | AJ13: =GHG!AE29 -> 21.761916 | AK13: =GHG!AF29 -> 18.498806 | AL13: =GHG!AG29 -> 18.498806 | AM13: =GHG!AH29 -> 18.498806 | AN13: =GHG!AI29 -> 21.867509 | AO13: =GHG!AJ29 -> 21.490163 | AP13: =GHG!B29 -> 0.088650607 | AQ13: =GHG!C29 -> 0.091640981 | AR13: =GHG!D29 -> 0.10324078 | AS13: =GHG!E29 -> 0.099169094 | AT13: =GHG!F29 -> 0.060540333 | AU13: =GHG!AB93 -> 0.008493912 | AV13: =GHG!AC93 -> 0.050963474 | AW13: =GHG!AD93 -> 0.0509635 | AX13: =GHG!AE93 -> 0.0509635 | AY13: =GHG!AF93 -> 0.050963474 | AZ13: =GHG!AG93 -> 0.0509635 | BA13: =GHG!AH93 -> 0.0509635 | BB13: =GHG!AI93 -> 0.050963474 | BC13: =GHG!AJ93 -> 0.050963474 | BD13: =GHG!B157 -> 0.004422464 | BE13: =GHG!C157 -> 0.004228687 | BF13: =GHG!D157 -> 0.004933914 | BG13: =GHG!E157 -> 0.004745273 | BH13: =GHG!F157 -> 0.003305503 | BI13: =GHG!AB157 -> 0.003074158 | BJ13: =GHG!AC157 -> 0.009222474 | BK13: =GHG!AD157 -> 0.0092225 | BL13: =GHG!AE157 -> 0.0092225 | BM13: =GHG!AF157 -> 0.009222474 | BN13: =GHG!AG157 -> 0.0092225 | BO13: =GHG!AH157 -> 0.0092225 | BP13: =GHG!AI157 -> 0.009222474 | BQ13: =GHG!AJ157 -> 0.009222474
A14: 6 | B14: =Originial!B25 -> 0.07 | C14: =Originial!C25 -> 0.05 | D14: =Originial!D25 -> 0.07 | E14: =Originial!E25 -> 0.05 | F14: =Originial!F25 -> 0.04 | G14: =Originial!H25 -> 60.93 | H14: =Originial!J25 -> 18.3 | I14: =Originial!N25 -> 5.02 | J14: =Originial!O25 -> 26.98 | K14: =Originial!P25 -> 17.56 | L14: =Originial!Q25 -> 17.36 | M14: =Originial!R25 -> 26.27 | N14: =Originial!S25 -> 24.12 | O14: =Originial!T25 -> 24.72 | P14: =Originial!U25 -> 29.38 | Q14: =Originial!V25 -> 26.05 | R14: =Originial!AE25 -> 0.017 | S14: =Originial!AO25 -> 0.22 | T14: =Originial!AP25 -> 0.15 | U14: =Originial!AQ25 -> 0.08 | V14: =Originial!AT25 -> 10.2 | W14: =Originial!AU25 -> 11.51 | X14: =Originial!AV25 -> 8.37 | Y14: =Originial!AY25 -> 26.98 | Z14: =Originial!AZ25 -> 17.56 | AA14: =Originial!BA25 -> 17.36 | AB14: =GHG!B30 -> 0.079481004 | AC14: =GHG!C30 -> 0.082219088 | AD14: =GHG!D30 -> 0.093202197 | AE14: =GHG!E30 -> 0.088827392 | AF14: =GHG!F30 -> 0.052915773 | AG14: =GHG!AB30 -> 15.88384 | AH14: =GHG!AC30 -> 22.140385 | AI14: =GHG!AD30 -> 22.140385 | AJ14: =GHG!AE30 -> 22.140385 | AK14: =GHG!AF30 -> 18.820524 | AL14: =GHG!AG30 -> 18.820524 | AM14: =GHG!AH30 -> 18.820524 | AN14: =GHG!AI30 -> 22.247813 | AO14: =GHG!AJ30 -> 21.863905 | AP14: =GHG!B30 -> 0.079481004 | AQ14: =GHG!C30 -> 0.082219088 | AR14: =GHG!D30 -> 0.093202197 | AS14: =GHG!E30 -> 0.088827392 | AT14: =GHG!F30 -> 0.052915773 | AU14: =GHG!AB94 -> 0.008653825 | AV14: =GHG!AC94 -> 0.051922949 | AW14: =GHG!AD94 -> 0.0519229 | AX14: =GHG!AE94 -> 0.0519229 | AY14: =GHG!AF94 -> 0.051922949 | AZ14: =GHG!AG94 -> 0.0519229 | BA14: =GHG!AH94 -> 0.0519229 | BB14: =GHG!AI94 -> 0.051922949 | BC14: =GHG!AJ94 -> 0.051922949 | BD14: =GHG!B158 -> 0.004132915 | BE14: =GHG!C158 -> 0.003960091 | BF14: =GHG!D158 -> 0.00467377 | BG14: =GHG!E158 -> 0.004448578 | BH14: =GHG!F158 -> 0.002984728 | BI14: =GHG!AB158 -> 0.003185457 | BJ14: =GHG!AC158 -> 0.009556371 | BK14: =GHG!AD158 -> 0.0095564 | BL14: =GHG!AE158 -> 0.0095564 | BM14: =GHG!AF158 -> 0.009556371 | BN14: =GHG!AG158 -> 0.0095564 | BO14: =GHG!AH158 -> 0.0095564 | BP14: =GHG!AI158 -> 0.009556371 | BQ14: =GHG!AJ158 -> 0.009556371
A15: 7 | B15: =Originial!B26 -> 0.06 | C15: =Originial!C26 -> 0.05 | D15: =Originial!D26 -> 0.06 | E15: =Originial!E26 -> 0.05 | F15: =Originial!F26 -> 0.04 | G15: =Originial!H26 -> 74.26 | H15: =Originial!J26 -> 18.29 | I15: =Originial!N26 -> 5.01 | J15: =Originial!O26 -> 26.83 | K15: =Originial!P26 -> 17.49 | L15: =Originial!Q26 -> 17.3 | M15: =Originial!R26 -> 27.07 | N15: =Originial!S26 -> 25.08 | O15: =Originial!T26 -> 26.16 | P15: =Originial!U26 -> 29.25 | Q15: =Originial!V26 -> 25.93 | R15: =Originial!AE26 -> 0.017 | S15: =Originial!AO26 -> 0.21 | T15: =Originial!AP26 -> 0.14 | U15: =Originial!AQ26 -> 0.08 | V15: =Originial!AT26 -> 10.71 | W15: =Originial!AU26 -> 12.01 | X15: =Originial!AV26 -> 9.1 | Y15: =Originial!AY26 -> 26.83 | Z15: =Originial!AZ26 -> 17.49 | AA15: =Originial!BA26 -> 17.3 | AB15: =GHG!B31 -> 0.069651313 | AC15: =GHG!C31 -> 0.072116304 | AD15: =GHG!D31 -> 0.082411304 | AE15: =GHG!E31 -> 0.077745126 | AF15: =GHG!F31 -> 0.044805496 | AG15: =GHG!AB31 -> 16.087479 | AH15: =GHG!AC31 -> 22.424236 | AI15: =GHG!AD31 -> 22.424236 | AJ15: =GHG!AE31 -> 22.424236 | AK15: =GHG!AF31 -> 19.061813 | AL15: =GHG!AG31 -> 19.061813 | AM15: =GHG!AH31 -> 19.061813 | AN15: =GHG!AI31 -> 22.533041 | AO15: =GHG!AJ31 -> 22.144211 | AP15: =GHG!B31 -> 0.069651313 | AQ15: =GHG!C31 -> 0.072116304 | AR15: =GHG!D31 -> 0.082411304 | AS15: =GHG!E31 -> 0.077745126 | AT15: =GHG!F31 -> 0.044805496 | AU15: =GHG!AB95 -> 0.008813737 | AV15: =GHG!AC95 -> 0.052882424 | AW15: =GHG!AD95 -> 0.0528824 | AX15: =GHG!AE95 -> 0.0528824 | AY15: =GHG!AF95 -> 0.052882424 | AZ15: =GHG!AG95 -> 0.0528824 | BA15: =GHG!AH95 -> 0.0528824 | BB15: =GHG!AI95 -> 0.052882424 | BC15: =GHG!AJ95 -> 0.052882424 | BD15: =GHG!B159 -> 0.003813423 | BE15: =GHG!C159 -> 0.003663448 | BF15: =GHG!D159 -> 0.004384665 | BG15: =GHG!E159 -> 0.004120744 | BH15: =GHG!F159 -> 0.002634196 | BI15: =GHG!AB159 -> 0.003298035 | BJ15: =GHG!AC159 -> 0.009894106 | BK15: =GHG!AD159 -> 0.0098941 | BL15: =GHG!AE159 -> 0.0098941 | BM15: =GHG!AF159 -> 0.009894106 | BN15: =GHG!AG159 -> 0.0098941 | BO15: =GHG!AH159 -> 0.0098941 | BP15: =GHG!AI159 -> 0.009894106 | BQ15: =GHG!AJ159 -> 0.009894106
A16: 8 | B16: =Originial!B27 -> 0.06 | C16: =Originial!C27 -> 0.05 | D16: =Originial!D27 -> 0.06 | E16: =Originial!E27 -> 0.05 | F16: =Originial!F27 -> 0.04 | G16: =Originial!H27 -> 67.34 | H16: =Originial!J27 -> 18.28 | I16: =Originial!N27 -> 5.01 | J16: =Originial!O27 -> 27.26 | K16: =Originial!P27 -> 17.79 | L16: =Originial!Q27 -> 17.6 | M16: =Originial!R27 -> 28.12 | N16: =Originial!S27 -> 26.22 | O16: =Originial!T27 -> 27.91 | P16: =Originial!U27 -> 29.67 | Q16: =Originial!V27 -> 25.83 | R16: =Originial!AE27 -> 0.017 | S16: =Originial!AO27 -> 0.22 | T16: =Originial!AP27 -> 0.14 | U16: =Originial!AQ27 -> 0.08 | V16: =Originial!AT27 -> 11.18 | W16: =Originial!AU27 -> 12.46 | X16: =Originial!AV27 -> 9.66 | Y16: =Originial!AY27 -> 27.26 | Z16: =Originial!AZ27 -> 17.79 | AA16: =Originial!BA27 -> 17.6 | AB16: =GHG!B32 -> 0.059795084 | AC16: =GHG!C32 -> 0.061988279 | AD16: =GHG!D32 -> 0.071614128 | AE16: =GHG!E32 -> 0.066629938 | AF16: =GHG!F32 -> 0.03662469 | AG16: =GHG!AB32 -> 16.358998 | AH16: =GHG!AC32 -> 22.802704 | AI16: =GHG!AD32 -> 22.802704 | AJ16: =GHG!AE32 -> 22.802704 | AK16: =GHG!AF32 -> 19.383531 | AL16: =GHG!AG32 -> 19.383531 | AM16: =GHG!AH32 -> 19.383531 | AN16: =GHG!AI32 -> 22.913346 | AO16: =GHG!AJ32 -> 22.517953 | AP16: =GHG!B32 -> 0.059795084 | AQ16: =GHG!C32 -> 0.061988279 | AR16: =GHG!D32 -> 0.071614128 | AS16: =GHG!E32 -> 0.066629938 | AT16: =GHG!F32 -> 0.03662469 | AU16: =GHG!AB96 -> 0.00897365 | AV16: =GHG!AC96 -> 0.053841899 | AW16: =GHG!AD96 -> 0.0538419 | AX16: =GHG!AE96 -> 0.0538419 | AY16: =GHG!AF96 -> 0.053841899 | AZ16: =GHG!AG96 -> 0.0538419 | BA16: =GHG!AH96 -> 0.0538419 | BB16: =GHG!AI96 -> 0.053841899 | BC16: =GHG!AJ96 -> 0.053841899 | BD16: =GHG!B160 -> 0.003462148 | BE16: =GHG!C160 -> 0.003336999 | BF16: =GHG!D160 -> 0.004064546 | BG16: =GHG!E160 -> 0.003759795 | BH16: =GHG!F160 -> 0.002252532 | BI16: =GHG!AB160 -> 0.003410614 | BJ16: =GHG!AC160 -> 0.010231841 | BK16: =GHG!AD160 -> 0.0102318 | BL16: =GHG!AE160 -> 0.0102318 | BM16: =GHG!AF160 -> 0.010231841 | BN16: =GHG!AG160 -> 0.0102318 | BO16: =GHG!AH160 -> 0.0102318 | BP16: =GHG!AI160 -> 0.010231841 | BQ16: =GHG!AJ160 -> 0.010231841
A17: 9 | B17: =Originial!B28 -> 0.06 | C17: =Originial!C28 -> 0.05 | D17: =Originial!D28 -> 0.06 | E17: =Originial!E28 -> 0.05 | F17: =Originial!F28 -> 0.04 | G17: =Originial!H28 -> 74.77 | H17: =Originial!J28 -> 18.27 | I17: =Originial!N28 -> 5 | J17: =Originial!O28 -> 27.43 | K17: =Originial!P28 -> 17.92 | L17: =Originial!Q28 -> 17.73 | M17: =Originial!R28 -> 29.04 | N17: =Originial!S28 -> 26.97 | O17: =Originial!T28 -> 29.09 | P17: =Originial!U28 -> 29.84 | Q17: =Originial!V28 -> 25.92 | R17: =Originial!AE28 -> 0.017 | S17: =Originial!AO28 -> 0.22 | T17: =Originial!AP28 -> 0.14 | U17: =Originial!AQ28 -> 0.08 | V17: =Originial!AT28 -> 11.49 | W17: =Originial!AU28 -> 12.72 | X17: =Originial!AV28 -> 9.95 | Y17: =Originial!AY28 -> 27.43 | Z17: =Originial!AZ28 -> 17.92 | AA17: =Originial!BA28 -> 17.73 | AB17: =GHG!B33 -> 0.049572655 | AC17: =GHG!C33 -> 0.051483651 | AD17: =GHG!D33 -> 0.060412369 | AE17: =GHG!E33 -> 0.055102224 | AF17: =GHG!F33 -> 0.02814722 | AG17: =GHG!AB33 -> 16.630516 | AH17: =GHG!AC33 -> 23.181172 | AI17: =GHG!AD33 -> 23.181172 | AJ17: =GHG!AE33 -> 23.181172 | AK17: =GHG!AF33 -> 19.70525 | AL17: =GHG!AG33 -> 19.70525 | AM17: =GHG!AH33 -> 19.70525 | AN17: =GHG!AI33 -> 23.29365 | AO17: =GHG!AJ33 -> 22.891695 | AP17: =GHG!B33 -> 0.049572655 | AQ17: =GHG!C33 -> 0.051483651 | AR17: =GHG!D33 -> 0.060412369 | AS17: =GHG!E33 -> 0.055102224 | AT17: =GHG!F33 -> 0.02814722 | AU17: =GHG!AB97 -> 0.009133434 | AV17: =GHG!AC97 -> 0.054800607 | AW17: =GHG!AD97 -> 0.0548006 | AX17: =GHG!AE97 -> 0.0548006 | AY17: =GHG!AF97 -> 0.054800607 | AZ17: =GHG!AG97 -> 0.0548006 | BA17: =GHG!AH97 -> 0.0548006 | BB17: =GHG!AI97 -> 0.054800607 | BC17: =GHG!AJ97 -> 0.054800607 | BD17: =GHG!B161 -> 0.003079089 | BE17: =GHG!C161 -> 0.002980744 | BF17: =GHG!D161 -> 0.003713413 | BG17: =GHG!E161 -> 0.003365732 | BH17: =GHG!F161 -> 0.001839736 | BI17: =GHG!AB161 -> 0.003523192 | BJ17: =GHG!AC161 -> 0.010569577 | BK17: =GHG!AD161 -> 0.0105696 | BL17: =GHG!AE161 -> 0.0105696 | BM17: =GHG!AF161 -> 0.010569577 | BN17: =GHG!AG161 -> 0.0105696 | BO17: =GHG!AH161 -> 0.0105696 | BP17: =GHG!AI161 -> 0.010569577 | BQ17: =GHG!AJ161 -> 0.010569577
A18: 10 | B18: =Originial!B29 -> 0.06 | C18: =Originial!C29 -> 0.05 | D18: =Originial!D29 -> 0.06 | E18: =Originial!E29 -> 0.05 | F18: =Originial!F29 -> 0.04 | G18: =Originial!H29 -> 81.46 | H18: =Originial!J29 -> 18.25 | I18: =Originial!N29 -> 5 | J18: =Originial!O29 -> 27.65 | K18: =Originial!P29 -> 18.13 | L18: =Originial!Q29 -> 17.94 | M18: =Originial!R29 -> 29.7 | N18: =Originial!S29 -> 27.32 | O18: =Originial!T29 -> 29.66 | P18: =Originial!U29 -> 30.15 | Q18: =Originial!V29 -> 25.71 | R18: =Originial!AE29 -> 0.017 | S18: =Originial!AO29 -> 0.22 | T18: =Originial!AP29 -> 0.15 | U18: =Originial!AQ29 -> 0.08 | V18: =Originial!AT29 -> 11.66 | W18: =Originial!AU29 -> 12.84 | X18: =Originial!AV29 -> 10.06 | Y18: =Originial!AY29 -> 27.65 | Z18: =Originial!AZ29 -> 18.13 | AA18: =Originial!BA29 -> 17.94 | AB18: =GHG!B34 -> 0.038827464 | AC18: =GHG!C34 -> 0.040439358 | AD18: =GHG!D34 -> 0.048610017 | AE18: =GHG!E34 -> 0.042988643 | AF18: =GHG!F34 -> 0.019295282 | AG18: =GHG!AB34 -> 16.834155 | AH18: =GHG!AC34 -> 23.465023 | AI18: =GHG!AD34 -> 23.465023 | AJ18: =GHG!AE34 -> 23.465023 | AK18: =GHG!AF34 -> 19.946539 | AL18: =GHG!AG34 -> 19.946539 | AM18: =GHG!AH34 -> 19.946539 | AN18: =GHG!AI34 -> 23.578879 | AO18: =GHG!AJ34 -> 23.172002 | AP18: =GHG!B34 -> 0.038827464 | AQ18: =GHG!C34 -> 0.040439358 | AR18: =GHG!D34 -> 0.048610017 | AS18: =GHG!E34 -> 0.042988643 | AT18: =GHG!F34 -> 0.019295282 | AU18: =GHG!AB98 -> 0.009293347 | AV18: =GHG!AC98 -> 0.055760082 | AW18: =GHG!AD98 -> 0.0557601 | AX18: =GHG!AE98 -> 0.0557601 | AY18: =GHG!AF98 -> 0.055760082 | AZ18: =GHG!AG98 -> 0.0557601 | BA18: =GHG!AH98 -> 0.0557601 | BB18: =GHG!AI98 -> 0.055760082 | BC18: =GHG!AJ98 -> 0.055760082 | BD18: =GHG!B162 -> 0.002664247 | BE18: =GHG!C162 -> 0.002594682 | BF18: =GHG!D162 -> 0.003331266 | BG18: =GHG!E162 -> 0.002938554 | BH18: =GHG!F162 -> 0.001395808 | BI18: =GHG!AB162 -> 0.003635771 | BJ18: =GHG!AC162 -> 0.010907312 | BK18: =GHG!AD162 -> 0.0109073 | BL18: =GHG!AE162 -> 0.0109073 | BM18: =GHG!AF162 -> 0.010907312 | BN18: =GHG!AG162 -> 0.0109073 | BO18: =GHG!AH162 -> 0.0109073 | BP18: =GHG!AI162 -> 0.010907312 | BQ18: =GHG!AJ162 -> 0.010907312
A19: 11 | B19: =Originial!B30 -> 0.06 | C19: =Originial!C30 -> 0.05 | D19: =Originial!D30 -> 0.06 | E19: =Originial!E30 -> 0.05 | F19: =Originial!F30 -> 0.04 | G19: =Originial!H30 -> 85.29 | H19: =Originial!J30 -> 18.25 | I19: =Originial!N30 -> 5 | J19: =Originial!O30 -> 27.69 | K19: =Originial!P30 -> 18.21 | L19: =Originial!Q30 -> 18.03 | M19: =Originial!R30 -> 30.1 | N19: =Originial!S30 -> 27.43 | O19: =Originial!T30 -> 29.84 | P19: =Originial!U30 -> 30.25 | Q19: =Originial!V30 -> 25.73 | R19: =Originial!AE30 -> 0.017 | S19: =Originial!AO30 -> 0.21 | T19: =Originial!AP30 -> 0.14 | U19: =Originial!AQ30 -> 0.08 | V19: =Originial!AT30 -> 11.71 | W19: =Originial!AU30 -> 12.83 | X19: =Originial!AV30 -> 10.02 | Y19: =Originial!AY30 -> 27.69 | Z19: =Originial!AZ30 -> 18.21 | AA19: =Originial!BA30 -> 18.03 | AB19: =GHG!B35 -> 0.037995779 | AC19: =GHG!C35 -> 0.038956439 | AD19: =GHG!D35 -> 0.045610629 | AE19: =GHG!E35 -> 0.04064978 | AF19: =GHG!F35 -> 0.019013858 | AG19: =GHG!AB35 -> 17.105674 | AH19: =GHG!AC35 -> 23.843491 | AI19: =GHG!AD35 -> 23.843491 | AJ19: =GHG!AE35 -> 23.843491 | AK19: =GHG!AF35 -> 20.268257 | AL19: =GHG!AG35 -> 20.268257 | AM19: =GHG!AH35 -> 20.268257 | AN19: =GHG!AI35 -> 23.959183 | AO19: =GHG!AJ35 -> 23.545743 | AP19: =GHG!B35 -> 0.037995779 | AQ19: =GHG!C35 -> 0.038956439 | AR19: =GHG!D35 -> 0.045610629 | AS19: =GHG!E35 -> 0.04064978 | AT19: =GHG!F35 -> 0.019013858 | AU19: =GHG!AB99 -> 0.009453259 | AV19: =GHG!AC99 -> 0.056719557 | AW19: =GHG!AD99 -> 0.0567196 | AX19: =GHG!AE99 -> 0.0567196 | AY19: =GHG!AF99 -> 0.056719557 | AZ19: =GHG!AG99 -> 0.0567196 | BA19: =GHG!AH99 -> 0.0567196 | BB19: =GHG!AI99 -> 0.056719557 | BC19: =GHG!AJ99 -> 0.056719557 | BD19: =GHG!B163 -> 0.002684271 | BE19: =GHG!C163 -> 0.002576548 | BF19: =GHG!D163 -> 0.003204965 | BG19: =GHG!E163 -> 0.002852019 | BH19: =GHG!F163 -> 0.001411075 | BI19: =GHG!AB163 -> 0.00374707 | BJ19: =GHG!AC163 -> 0.011241209 | BK19: =GHG!AD163 -> 0.0112412 | BL19: =GHG!AE163 -> 0.0112412 | BM19: =GHG!AF163 -> 0.011241209 | BN19: =GHG!AG163 -> 0.0112412 | BO19: =GHG!AH163 -> 0.0112412 | BP19: =GHG!AI163 -> 0.011241209 | BQ19: =GHG!AJ163 -> 0.011241209
A20: 12 | B20: =Originial!B31 -> 0.06 | C20: =Originial!C31 -> 0.05 | D20: =Originial!D31 -> 0.06 | E20: =Originial!E31 -> 0.05 | F20: =Originial!F31 -> 0.04 | G20: =Originial!H31 -> 87.17 | H20: =Originial!J31 -> 18.24 | I20: =Originial!N31 -> 4.99 | J20: =Originial!O31 -> 27.91 | K20: =Originial!P31 -> 18.38 | L20: =Originial!Q31 -> 18.21 | M20: =Originial!R31 -> 30.32 | N20: =Originial!S31 -> 27.46 | O20: =Originial!T31 -> 29.89 | P20: =Originial!U31 -> 30.47 | Q20: =Originial!V31 -> 25.65 | R20: =Originial!AE31 -> 0.017 | S20: =Originial!AO31 -> 0.22 | T20: =Originial!AP31 -> 0.14 | U20: =Originial!AQ31 -> 0.08 | V20: =Originial!AT31 -> 11.68 | W20: =Originial!AU31 -> 12.75 | X20: =Originial!AV31 -> 9.87 | Y20: =Originial!AY31 -> 27.91 | Z20: =Originial!AZ31 -> 18.38 | AA20: =Originial!BA31 -> 18.21 | AB20: =GHG!B36 -> 0.037117811 | AC20: =GHG!C36 -> 0.037405737 | AD20: =GHG!D36 -> 0.042491133 | AE20: =GHG!E36 -> 0.038214655 | AF20: =GHG!F36 -> 0.01871362 | AG20: =GHG!AB36 -> 17.377192 | AH20: =GHG!AC36 -> 24.221959 | AI20: =GHG!AD36 -> 24.221959 | AJ20: =GHG!AE36 -> 24.221959 | AK20: =GHG!AF36 -> 20.589975 | AL20: =GHG!AG36 -> 20.589975 | AM20: =GHG!AH36 -> 20.589975 | AN20: =GHG!AI36 -> 24.339488 | AO20: =GHG!AJ36 -> 23.919485 | AP20: =GHG!B36 -> 0.037117811 | AQ20: =GHG!C36 -> 0.037405737 | AR20: =GHG!D36 -> 0.042491133 | AS20: =GHG!E36 -> 0.038214655 | AT20: =GHG!F36 -> 0.01871362 | AU20: =GHG!AB100 -> 0.009613172 | AV20: =GHG!AC100 -> 0.057679032 | AW20: =GHG!AD100 -> 0.057679 | AX20: =GHG!AE100 -> 0.057679 | AY20: =GHG!AF100 -> 0.057679032 | AZ20: =GHG!AG100 -> 0.057679 | BA20: =GHG!AH100 -> 0.057679 | BB20: =GHG!AI100 -> 0.057679032 | BC20: =GHG!AJ100 -> 0.057679032 | BD20: =GHG!B164 -> 0.002701535 | BE20: =GHG!C164 -> 0.002553465 | BF20: =GHG!D164 -> 0.003066119 | BG20: =GHG!E164 -> 0.002755913 | BH20: =GHG!F164 -> 0.001425183 | BI20: =GHG!AB164 -> 0.003859648 | BJ20: =GHG!AC164 -> 0.011578944 | BK20: =GHG!AD164 -> 0.0115789 | BL20: =GHG!AE164 -> 0.0115789 | BM20: =GHG!AF164 -> 0.011578944 | BN20: =GHG!AG164 -> 0.0115789 | BO20: =GHG!AH164 -> 0.0115789 | BP20: =GHG!AI164 -> 0.011578944 | BQ20: =GHG!AJ164 -> 0.011578944
... A58: 50 | B58: =Originial!B69 -> 0.08 | C58: =Originial!C69 -> 0.06 | D58: =Originial!D69 -> 0.08 | E58: =Originial!E69 -> 0.06 | F58: =Originial!F69 -> 0.05 | G58: =Originial!H69 -> 81.71 | H58: =Originial!J69 -> 17.1 | I58: =Originial!N69 -> 4.68 | J58: =Originial!O69 -> 31.29 | K58: =Originial!P69 -> 20.55 | L58: =Originial!Q69 -> 20.34 | M58: =Originial!R69 -> 33.23 | N58: =Originial!S69 -> 29.95 | O58: =Originial!T69 -> 33.93 | P58: =Originial!U69 -> 33.13 | Q58: =Originial!V69 -> 23.79 | R58: =Originial!AE69 -> 0.017 | S58: =Originial!AO69 -> 0.25 | T58: =Originial!AP69 -> 0.17 | U58: =Originial!AQ69 -> 0.09 | V58: =Originial!AT69 -> 12.35 | W58: =Originial!AU69 -> 12.92 | X58: =Originial!AV69 -> 9.61 | Y58: =Originial!AY69 -> 31.29 | Z58: =Originial!AZ69 -> 20.55 | AA58: =Originial!BA69 -> 20.34 | AB58: =GHG!B74 -> 0.026914777 | AC58: =GHG!C74 -> 0.025706768 | AD58: =GHG!D74 -> 0.033554617 | AE58: =GHG!E74 -> 0.029965821 | AF58: =GHG!F74 -> 0.01417027 | AG58: =GHG!AB74 -> 20.906935 | AH58: =GHG!AC74 -> 29.142045 | AI58: =GHG!AD74 -> 29.142045 | AJ58: =GHG!AE74 -> 29.142045 | AK58: =GHG!AF74 -> 24.772314 | AL58: =GHG!AG74 -> 24.772314 | AM58: =GHG!AH74 -> 24.772314 | AN58: =GHG!AI74 -> 29.283446 | AO58: =GHG!AJ74 -> 28.778131 | AP58: =GHG!B74 -> 0.026914777 | AQ58: =GHG!C74 -> 0.025706768 | AR58: =GHG!D74 -> 0.033554617 | AS58: =GHG!E74 -> 0.029965821 | AT58: =GHG!F74 -> 0.01417027 | AU58: =GHG!AB138 -> 0.011896978 | AV58: =GHG!AC138 -> 0.07138187 | AW58: =GHG!AD138 -> 0.0713819 | AX58: =GHG!AE138 -> 0.0713819 | AY58: =GHG!AF138 -> 0.07138187 | AZ58: =GHG!AG138 -> 0.0713819 | BA58: =GHG!AH138 -> 0.0713819 | BB58: =GHG!AI138 -> 0.07138187 | BC58: =GHG!AJ138 -> 0.07138187 | BD58: =GHG!B202 -> 0.002480229 | BE58: =GHG!C202 -> 0.002249242 | BF58: =GHG!D202 -> 0.003045056 | BG58: =GHG!E202 -> 0.00271828 | BH58: =GHG!F202 -> 0.001314623 | BI58: =GHG!AB202 -> 0.005412718 | BJ58: =GHG!AC202 -> 0.016238155 | BK58: =GHG!AD202 -> 0.0162382 | BL58: =GHG!AE202 -> 0.0162382 | BM58: =GHG!AF202 -> 0.016238155 | BN58: =GHG!AG202 -> 0.0162382 | BO58: =GHG!AH202 -> 0.0162382 | BP58: =GHG!AI202 -> 0.016238155 | BQ58: =GHG!AJ202 -> 0.016238155

Sheet Originial
A1: Avoided Costs & Fuel Prices | E1: All Avoided Costs must be in Year 2026$ | M1: END-USE FUEL COSTS
B3: LINE LOSS FACTORS (% of meter) | M3: RETAIL FUEL COST ADDERS ($/MMBtu) | AI3: EMISSIONS IMPACTS | AM3: $/tonne CO2
A4: Sectors | B4: Summer On-Peak | C4: Summer Off-Peak | D4: Winter On-Peak | E4: Winter Off-Peak | F4: Shoulder | H4: Summer Gener. Capacity | J4: Summer T&D | M4: Sectors | N4: Natural Gas | O4: 0 | P4: 0 | Q4: 0 | R4: 0 | S4: 0 | AI4: CO2 | AJ4: NOx | AK4: CH4 | AL4: Equivalent CO2 Externalities
A5: Res | B5: 0.1 | C5: 0.1 | D5: 0.1 | E5: 0.1 | F5: 0.1 | H5: 0.241 | J5: 0.241 | M5: Res | AH5: Electric (tonne/MWh at gen) | AI5: 0 | AJ5: 0 | AK5: 0 | AL5: $- | AM5: $/kWh | AO5: 1 tonne = 1 "metric ton"
A6: Small C&I | B6: 0.0895 | C6: 0.0895 | D6: 0.0895 | E6: 0.0895 | F6: 0.0895 | H6: 0.241 | J6: 0.241 | M6: Small C&I | AH6: Nat Gas (tonne/MMBtu) | AI6: 0.05306 | AJ6: 1e-07 | AK6: 1e-06 | AL6: $- | AM6: $/MMBtu | AO6: 1 US short ton = 2000 lbs
A7: Large C&I | B7: 0.0895 | C7: 0.0895 | D7: 0.0895 | E7: 0.0895 | F7: 0.0895 | H7: 0.241 | J7: 0.241 | M7: Large C&I | AH7: Oil (tonne/MMBtu) | AI7: 0.07396 | AJ7: 6e-07 | AK7: 3e-06 | AL7: $- | AM7: $/MMBtu | AO7: 1.102 | AP7: US short ton/tonne
AO8: 0.00892 | AP8: tonne CO2/gallon of gas | AS8: http://www.epa.gov/cleanenergy/energy-resources/refs.html
AL9: $- | AM9: $/gallon of gas equivalent for cost of CO2 (combustion CO2 only)
N11: USER DEFINED END-USE EXTERNALITIES ($/MMBtu)
N12: 0
B14: ELECTRIC AVOIDED COSTS w/o losses (at gen) | G14: 1 | H14: Electric Avoided Costs Multiplier | N14: 1 | O14: End-use Fuel Costs Multiplier | AE14: OTHER RESOURCE | AH14: USER DEFINED | AO14: RETAIL PRICES BY SECTOR (2026$) - For the Participant Test | BE14: ELEC SALES & RIM INPUTS
B15: kWh1 | C15: kWh2 | D15: kWh3 | E15: kWh4 | F15: kWh5 | G15: kWh6 | H15: kW1 | I15: kW2 | J15: kW3 | K15: kW4 | N15: 1 | O15: 2 | P15: 3 | Q15: 4 | R15: 5 | S15: 6 | T15: 7 | U15: 8 | V15: 9 | W15: 10 | X15: 11 | Y15: 12 | Z15: 13 | AA15: 14 | AB15: 15 | AC15: 16 | AE15: AVOIDED COSTS | AH15: ELECTRIC EXTERNALITIES without losses (at gen) | AO15: ELECTRICITY | AT15: NATURAL GAS | AY15: HEATING OIL | BE15: Base Case
A16: Period/ | B16: Summer On-Peak | C16: Summer Off-Peak | D16: Winter On-Peak | E16: Winter Off-Peak | F16: Shoulder | H16: Summer Gener. Capacity | I16: winter_gener_capacity_usdperkW-yr | J16: Summer T&D | K16: winter_td_usdperkW-yr | N16: Natural Gas | O16: Res Fuel Oil | P16: Com Fuel Oil | Q16: Ind Fuel Oil | R16: Res Propane | S16: Com Propane | T16: Ind Propane | U16: Diesel, Transportation | V16: Gasoline, Transportation | AE16: Water | AH16: Summer On-Peak | AI16: Summer Off-Peak | AJ16: Winter On-Peak | AK16: Winter Off-Peak | AL16: Shoulder On-Peak | AM16: Shoulder Off-Peak | AO16: Res | AP16: Commercial | AQ16: Industrial | AR16: 0 | AS16: 0 | AT16: Res | AU16: Commercial | AV16: Industrial | AW16: 0 | AX16: 0 | AY16: Res | AZ16: Commercial | BA16: Industrial | BB16: 0 | BC16: 0 | BE16: Annual Revenue Requirement | BF16: Annual Native Sales
A17: Type:
M18: Fuel Class: | N18: Natural Gas | O18: Oil | P18: Oil | Q18: Oil | R18: Propane | S18: Propane | T18: Propane | U18: Oil | V18: Oil | BE18: (2026$)
B19: $/kWh | C19: $/kWh | D19: $/kWh | E19: $/kWh | F19: $/kWh | G19: $/kWh | H19: $/kW-yr | I19: $/kW-yr | J19: $/kW-yr | K19: $/kW-yr | N19: $/MMBtu | O19: $/MMBtu | P19: $/MMBtu | Q19: $/MMBtu | R19: $/MMBtu | S19: $/MMBtu | T19: $/MMBtu | U19: $/MMBtu | V19: $/MMBtu | W19: $/MMBtu | X19: $/MMBtu | Y19: $/MMBtu | Z19: $/MMBtu | AA19: $/MMBtu | AB19: $/MMBtu | AC19: $/MMBtu | AE19: $/Gallon | AF19: $/ | AH19: $/kWh | AI19: $/kWh | AJ19: $/kWh | AK19: $/kWh | AL19: $/kWh | AM19: $/kWh | AO19: $/kWh | AP19: $/kWh | AQ19: $/kWh | AR19: $/kWh | AS19: $/kWh | AT19: $/MMBtu | AU19: $/MMBtu | AV19: $/MMBtu | AW19: $/MMBtu | AX19: $/MMBtu | AY19: $/MMBtu | AZ19: $/MMBtu | BA19: $/MMBtu | BB19: $/MMBtu | BC19: $/MMBtu | BE19: $Million | BF19: GWh
A20: 2026 | B20: 0.06 | C20: 0.04 | D20: 0.06 | E20: 0.04 | F20: 0.04 | H20: 89.69 | I20: 0 | J20: 18.6 | K20: 0 | N20: 5.62 | O20: 24.68 | P20: 18.71 | Q20: 18.71 | R20: 25.38 | S20: 22.83 | T20: 22.83 | U20: 28.12 | V20: 27.09 | AE20: 0.017 | AO20: 0.2 | AP20: 0.14 | AQ20: 0.08 | AT20: 11.26 | AU20: 9.77 | AV20: 7.91 | AY20: 24.68 | AZ20: 18.71 | BA20: 18.71
A21: 2027 | B21: 0.06 | C21: 0.05 | D21: 0.06 | E21: 0.05 | F21: 0.04 | H21: 49.6 | I21: 0 | J21: 18.32 | K21: 0 | N21: 4.73 | O21: 25 | P21: 18.24 | Q21: 18.19 | R21: 25.19 | S21: 22.61 | T21: 22.51 | U21: 28.19 | V21: 26.53 | AE21: 0.017 | AO21: 0.21 | AP21: 0.14 | AQ21: 0.08 | AT21: 10.72 | AU21: 9.96 | AV21: 7.69 | AY21: 25 | AZ21: 18.24 | BA21: 18.19
A22: 2028 | B22: 0.06 | C22: 0.05 | D22: 0.06 | E22: 0.05 | F22: 0.04 | H22: 42.36 | I22: 0 | J22: 18.31 | K22: 0 | N22: 4.71 | O22: 25.57 | P22: 17.97 | Q22: 17.87 | R22: 25.19 | S22: 22.75 | T22: 22.7 | U22: 28.53 | V22: 26.25 | AE22: 0.017 | AO22: 0.21 | AP22: 0.14 | AQ22: 0.08 | AT22: 10.38 | AU22: 10.34 | AV22: 7.76 | AY22: 25.57 | AZ22: 17.97 | BA22: 17.87
A23: 2029 | B23: 0.06 | C23: 0.05 | D23: 0.06 | E23: 0.05 | F23: 0.04 | H23: 63.21 | I23: 0 | J23: 18.3 | K23: 0 | N23: 4.59 | O23: 26.19 | P23: 17.72 | Q23: 17.57 | R23: 25.4 | S23: 23.11 | T23: 23.23 | U23: 28.89 | V23: 25.94 | AE23: 0.017 | AO23: 0.22 | AP23: 0.14 | AQ23: 0.08 | AT23: 10.19 | AU23: 10.84 | AV23: 7.94 | AY23: 26.19 | AZ23: 17.72 | BA23: 17.57
A24: 2030 | B24: 0.07 | C24: 0.05 | D24: 0.07 | E24: 0.05 | F24: 0.04 | H24: 57.55 | I24: 0 | J24: 18.29 | K24: 0 | N24: 5.02 | O24: 26.88 | P24: 17.5 | Q24: 17.3 | R24: 25.8 | S24: 23.63 | T24: 23.99 | U24: 29.3 | V24: 26 | AE24: 0.017 | AO24: 0.22 | AP24: 0.15 | AQ24: 0.08 | AT24: 9.98 | AU24: 11.31 | AV24: 8.15 | AY24: 26.88 | AZ24: 17.5 | BA24: 17.3
A25: 2031 | B25: 0.07 | C25: 0.05 | D25: 0.07 | E25: 0.05 | F25: 0.04 | H25: 60.93 | I25: 0 | J25: 18.3 | K25: 0 | N25: 5.02 | O25: 26.98 | P25: 17.56 | Q25: 17.36 | R25: 26.27 | S25: 24.12 | T25: 24.72 | U25: 29.38 | V25: 26.05 | AE25: 0.017 | AO25: 0.22 | AP25: 0.15 | AQ25: 0.08 | AT25: 10.2 | AU25: 11.51 | AV25: 8.37 | AY25: 26.98 | AZ25: 17.56 | BA25: 17.36
A26: 2032 | B26: 0.06 | C26: 0.05 | D26: 0.06 | E26: 0.05 | F26: 0.04 | H26: 74.26 | I26: 0 | J26: 18.29 | K26: 0 | N26: 5.01 | O26: 26.83 | P26: 17.49 | Q26: 17.3 | R26: 27.07 | S26: 25.08 | T26: 26.16 | U26: 29.25 | V26: 25.93 | AE26: 0.017 | AO26: 0.21 | AP26: 0.14 | AQ26: 0.08 | AT26: 10.71 | AU26: 12.01 | AV26: 9.1 | AY26: 26.83 | AZ26: 17.49 | BA26: 17.3
A27: 2033 | B27: 0.06 | C27: 0.05 | D27: 0.06 | E27: 0.05 | F27: 0.04 | H27: 67.34 | I27: 0 | J27: 18.28 | K27: 0 | N27: 5.01 | O27: 27.26 | P27: 17.79 | Q27: 17.6 | R27: 28.12 | S27: 26.22 | T27: 27.91 | U27: 29.67 | V27: 25.83 | AE27: 0.017 | AO27: 0.22 | AP27: 0.14 | AQ27: 0.08 | AT27: 11.18 | AU27: 12.46 | AV27: 9.66 | AY27: 27.26 | AZ27: 17.79 | BA27: 17.6
A28: 2034 | B28: 0.06 | C28: 0.05 | D28: 0.06 | E28: 0.05 | F28: 0.04 | H28: 74.77 | I28: 0 | J28: 18.27 | K28: 0 | N28: 5 | O28: 27.43 | P28: 17.92 | Q28: 17.73 | R28: 29.04 | S28: 26.97 | T28: 29.09 | U28: 29.84 | V28: 25.92 | AE28: 0.017 | AO28: 0.22 | AP28: 0.14 | AQ28: 0.08 | AT28: 11.49 | AU28: 12.72 | AV28: 9.95 | AY28: 27.43 | AZ28: 17.92 | BA28: 17.73
A29: 2035 | B29: 0.06 | C29: 0.05 | D29: 0.06 | E29: 0.05 | F29: 0.04 | H29: 81.46 | I29: 0 | J29: 18.25 | K29: 0 | N29: 5 | O29: 27.65 | P29: 18.13 | Q29: 17.94 | R29: 29.7 | S29: 27.32 | T29: 29.66 | U29: 30.15 | V29: 25.71 | AE29: 0.017 | AO29: 0.22 | AP29: 0.15 | AQ29: 0.08 | AT29: 11.66 | AU29: 12.84 | AV29: 10.06 | AY29: 27.65 | AZ29: 18.13 | BA29: 17.94
A30: 2036 | B30: 0.06 | C30: 0.05 | D30: 0.06 | E30: 0.05 | F30: 0.04 | H30: 85.29 | I30: 0 | J30: 18.25 | K30: 0 | N30: 5 | O30: 27.69 | P30: 18.21 | Q30: 18.03 | R30: 30.1 | S30: 27.43 | T30: 29.84 | U30: 30.25 | V30: 25.73 | AE30: 0.017 | AO30: 0.21 | AP30: 0.14 | AQ30: 0.08 | AT30: 11.71 | AU30: 12.83 | AV30: 10.02 | AY30: 27.69 | AZ30: 18.21 | BA30: 18.03
A31: 2037 | B31: 0.06 | C31: 0.05 | D31: 0.06 | E31: 0.05 | F31: 0.04 | H31: 87.17 | I31: 0 | J31: 18.24 | K31: 0 | N31: 4.99 | O31: 27.91 | P31: 18.38 | Q31: 18.21 | R31: 30.32 | S31: 27.46 | T31: 29.89 | U31: 30.47 | V31: 25.65 | AE31: 0.017 | AO31: 0.22 | AP31: 0.14 | AQ31: 0.08 | AT31: 11.68 | AU31: 12.75 | AV31: 9.87 | AY31: 27.91 | AZ31: 18.38 | BA31: 18.21
... A69: 2075 | B69: 0.08 | C69: 0.06 | D69: 0.08 | E69: 0.06 | F69: 0.05 | H69: 81.71 | I69: 0 | J69: 17.1 | K69: 0 | N69: 4.68 | O69: 31.29 | P69: 20.55 | Q69: 20.34 | R69: 33.23 | S69: 29.95 | T69: 33.93 | U69: 33.13 | V69: 23.79 | AE69: 0.017 | AO69: 0.25 | AP69: 0.17 | AQ69: 0.09 | AT69: 12.35 | AU69: 12.92 | AV69: 9.61 | AY69: 31.29 | AZ69: 20.55 | BA69: 20.34

Sheet GHG
C2: EMISSIONS IMPACTS | G2: $/tonne CO2
C3: CO2 | D3: NOx | E3: CH4 | F3: Equivalent CO2 Externalities | J3: kg to tonne | K3: 1000
B4: Electric (tonne/MWh at gen) | F4: $- | G4: $/kWh | I4: 1 tonne = 1 "metric ton" | J4: gram to tonne | K4: 1000000 | Q4: 53851963000
B5: Nat Gas (tonne/MMBtu) | C5: 0.05306 | D5: 1e-07 | E5: 1e-06 | F5: $- | G5: $/MMBtu | I5: 1 US short ton = 2000 lbs | Q5: 33692992000
B6: Oil (tonne/MMBtu) | C6: 0.07396 | D6: 6e-07 | E6: 3e-06 | F6: $- | G6: $/MMBtu | I6: 1.102 | Q6: 703489000 | AI6: Diesel (MMBtu/gal) | AJ6: Gasoline (MMBtu/gal)
I7: 0.00892 | Q7: 92642031663 | R7: 0.952575 | AI7: 0.137381 | AJ7: 0.120214
F8: $- | G8: $/gallon of gas equivalent for cost of CO2 (combustion CO2 only)
AI9: https://www.eia.gov/energyexplained/units-and-calculators/
G10: https://www.epa.gov/system/files/other-files/2025-01/ghg-emission-factors-hub-2025.xlsx
B12: CO2 Version | G12: U.S. Energy Information Administration - EIA - Independent Statistics and Analysis
B13: USER DEFINED | N13: USER DEFINED | AA13: Emissions Factors (tonnes/MMBtu) | AB13: 0.05306 | AC13: 0.07396 | AD13: 0.07396 | AE13: 0.07396 | AF13: 0.06287 | AG13: 0.06287 | AH13: 0.06287 | AI13: 0.074318865 | AJ13: 0.073036418
B14: ELECTRIC EXTERNALITIES without losses (at gen) | N14: ELECTRIC EXTERNALITIES without losses (at gen) | AB14: 1 | AC14: 2 | AD14: 3 | AE14: 4 | AF14: 5 | AG14: 6 | AH14: 7 | AI14: 8 | AJ14: 9
B15: Summer On-Peak | C15: Summer Off-Peak | D15: Winter On-Peak | E15: Winter Off-Peak | F15: Shoulder On-Peak | G15: Shoulder Off-Peak | N15: Summer On-Peak | O15: Summer Off-Peak | P15: Winter On-Peak | Q15: Winter Off-Peak | R15: Shoulder On-Peak | S15: Shoulder Off-Peak | AB15: Natural Gas | AC15: Res Fuel Oil | AD15: Com Fuel Oil | AE15: Ind Fuel Oil | AF15: Res Propane | AG15: Com Propane | AH15: Ind Propane | AI15: Diesel, Transportation | AJ15: Gasoline, Transportation
AN16: Cost of Carbon $/MMBtu
AB17: Natural Gas | AC17: Oil | AD17: Oil | AE17: Oil | AF17: Propane | AG17: Propane | AH17: Propane | AI17: Oil | AJ17: Oil | AM17: Year | AN17: Natural Gas | AO17: Res Fuel Oil | AP17: Com Fuel Oil | AQ17: Ind Fuel Oil | AR17: Res Propane | AS17: Com Propane | AT17: Ind Propane | AU17: Diesel, Transportation | AV17: Gasoline, Transportation
B18: $/kWh | C18: $/kWh | D18: $/kWh | E18: $/kWh | F18: $/kWh | G18: $/kWh | N18: $/tonne | O18: $/tonne | P18: $/tonne | Q18: $/tonne | R18: $/tonne | S18: $/tonne | AB18: $/MMBtu | AC18: $/MMBtu | AD18: $/MMBtu | AE18: $/MMBtu | AF18: $/MMBtu | AG18: $/MMBtu | AH18: $/MMBtu | AI18: $/MMBtu | AJ18: $/MMBtu | AM18: 2026 | AN18: 14.605 | AO18: 20.398 | AP18: 20.398 | AQ18: 20.398 | AR18: 17.348 | AS18: 17.348 | AT18: 17.348 | AU18: 20.497 | AV18: 20.144
A19: 2020 | M19: 2020 | AM19: 2030 | AN19: 15.624 | AO19: 21.822 | AP19: 21.822 | AQ19: 21.822 | AR19: 18.559 | AS19: 18.559 | AT19: 18.559 | AU19: 21.928 | AV19: 21.55
A20: 2021 | M20: 2021 | AM20: 2035 | AN20: 16.847 | AO20: 23.532 | AP20: 23.532 | AQ20: 23.532 | AR20: 20.013 | AS20: 20.013 | AT20: 20.013 | AU20: 23.646 | AV20: 23.239
A21: 2022 | M21: 2022 | AM21: 2040 | AN21: 18.138 | AO21: 25.336 | AP21: 25.336 | AQ21: 25.336 | AR21: 21.548 | AS21: 21.548 | AT21: 21.548 | AU21: 25.458 | AV21: 25.02
A22: 2023 | M22: 2023 | AM22: 2045 | AN22: 19.497 | AO22: 27.235 | AP22: 27.235 | AQ22: 27.235 | AR22: 23.164 | AS22: 23.164 | AT22: 23.164 | AU22: 27.367 | AV22: 26.896
A23: 2024 | M23: 2024 | AM23: 2050 | AN23: 20.924 | AO23: 29.23 | AP23: 29.23 | AQ23: 29.23 | AR23: 24.86 | AS23: 24.86 | AT23: 24.86 | AU23: 29.371 | AV23: 28.866
A24: 2025 | B24: 0.07456699 | M24: 2025
A25: 2026 | B25: 0.077749014 | C25: 0.075741179 | D25: 0.084995875 | E25: 0.08228085 | F25: 0.05206803 | G25: 0.05206803 | I25: add all ghg for all years average for all period level values then average | M25: 2026 | N25: 275.0495 | O25: 275.0495 | P25: 275.0495 | Q25: 275.0495 | R25: 275.0495 | S25: 275.0495 | AA25: 2026 | AB25: 14.594126 | AC25: 20.342661 | AD25: 20.342661 | AE25: 20.342661 | AF25: 17.292362 | AG25: 17.292362 | AH25: 17.292362 | AI25: 20.441367 | AJ25: 20.08863
A26: 2027 | B26: 0.080499329 | C26: 0.079677276 | D26: 0.089508689 | E26: 0.086465299 | F26: 0.054188785 | G26: 0.054188785 | I26: just do every 5 years | M26: 2027 | N26: 280.1667 | O26: 280.1667 | P26: 280.1667 | Q26: 280.1667 | R26: 280.1667 | S26: 280.1667 | U26: EPA Report on the Social Cost of Greenhouse Gases: Estimates Incorporating Recent Scientific Advances | AA26: 2027 | AB26: 14.865645 | AC26: 20.721129 | AD26: 20.721129 | AE26: 20.721129 | AF26: 17.61408 | AG26: 17.61408 | AH26: 17.61408 | AI26: 20.821671 | AJ26: 20.462372
A27: 2028 | B27: 0.083297273 | C27: 0.083705682 | D27: 0.09412859 | E27: 0.090746684 | F27: 0.056351623 | G27: 0.056351623 | M27: 2028 | N27: 285.2839 | O27: 285.2839 | P27: 285.2839 | Q27: 285.2839 | R27: 285.2839 | S27: 285.2839 | AA27: 2028 | AB27: 15.137164 | AC27: 21.099597 | AD27: 21.099597 | AE27: 21.099597 | AF27: 17.935799 | AG27: 17.935799 | AH27: 17.935799 | AI27: 21.201976 | AJ27: 20.836114
A28: 2029 | B28: 0.085763361 | C28: 0.087439496 | D28: 0.09842009 | E28: 0.094705953 | F28: 0.058298587 | G28: 0.058298587 | M28: 2029 | N28: 289.1218 | O28: 289.1218 | P28: 289.1218 | Q28: 289.1218 | R28: 289.1218 | S28: 289.1218 | AA28: 2029 | AB28: 15.340803 | AC28: 21.383448 | AD28: 21.383448 | AE28: 21.383448 | AF28: 18.177088 | AG28: 18.177088 | AH28: 18.177088 | AI28: 21.487204 | AJ28: 21.116421
A29: 2030 | B29: 0.088650607 | C29: 0.091640981 | D29: 0.10324078 | E29: 0.099169094 | F29: 0.060540333 | G29: 0.060540333 | M29: 2030 | N29: 294.239 | O29: 294.239 | P29: 294.239 | Q29: 294.239 | R29: 294.239 | S29: 294.239 | AA29: 2030 | AB29: 15.612321 | AC29: 21.761916 | AD29: 21.761916 | AE29: 21.761916 | AF29: 18.498806 | AG29: 18.498806 | AH29: 18.498806 | AI29: 21.867509 | AJ29: 21.490163
A30: 2031 | B30: 0.079481004 | C30: 0.082219088 | D30: 0.093202197 | E30: 0.088827392 | F30: 0.052915773 | G30: 0.052915773 | M30: 2031 | N30: 299.3562 | O30: 299.3562 | P30: 299.3562 | Q30: 299.3562 | R30: 299.3562 | S30: 299.3562 | AA30: 2031 | AB30: 15.88384 | AC30: 22.140385 | AD30: 22.140385 | AE30: 22.140385 | AF30: 18.820524 | AG30: 18.820524 | AH30: 18.820524 | AI30: 22.247813 | AJ30: 21.863905
A31: 2032 | B31: 0.069651313 | C31: 0.072116304 | D31: 0.082411304 | E31: 0.077745126 | F31: 0.044805496 | G31: 0.044805496 | M31: 2032 | N31: 303.1941 | O31: 303.1941 | P31: 303.1941 | Q31: 303.1941 | R31: 303.1941 | S31: 303.1941 | AA31: 2032 | AB31: 16.087479 | AC31: 22.424236 | AD31: 22.424236 | AE31: 22.424236 | AF31: 19.061813 | AG31: 19.061813 | AH31: 19.061813 | AI31: 22.533041 | AJ31: 22.144211
A32: 2033 | B32: 0.059795084 | C32: 0.061988279 | D32: 0.071614128 | E32: 0.066629938 | F32: 0.03662469 | G32: 0.03662469 | M32: 2033 | N32: 308.3113 | O32: 308.3113 | P32: 308.3113 | Q32: 308.3113 | R32: 308.3113 | S32: 308.3113 | AA32: 2033 | AB32: 16.358998 | AC32: 22.802704 | AD32: 22.802704 | AE32: 22.802704 | AF32: 19.383531 | AG32: 19.383531 | AH32: 19.383531 | AI32: 22.913346 | AJ32: 22.517953
A33: 2034 | B33: 0.049572655 | C33: 0.051483651 | D33: 0.060412369 | E33: 0.055102224 | F33: 0.02814722 | G33: 0.02814722 | M33: 2034 | N33: 313.4285 | O33: 313.4285 | P33: 313.4285 | Q33: 313.4285 | R33: 313.4285 | S33: 313.4285 | AA33: 2034 | AB33: 16.630516 | AC33: 23.181172 | AD33: 23.181172 | AE33: 23.181172 | AF33: 19.70525 | AG33: 19.70525 | AH33: 19.70525 | AI33: 23.29365 | AJ33: 22.891695
A34: 2035 | B34: 0.038827464 | C34: 0.040439358 | D34: 0.048610017 | E34: 0.042988643 | F34: 0.019295282 | G34: 0.019295282 | M34: 2035 | N34: 317.2664 | O34: 317.2664 | P34: 317.2664 | Q34: 317.2664 | R34: 317.2664 | S34: 317.2664 | AA34: 2035 | AB34: 16.834155 | AC34: 23.465023 | AD34: 23.465023 | AE34: 23.465023 | AF34: 19.946539 | AG34: 19.946539 | AH34: 19.946539 | AI34: 23.578879 | AJ34: 23.172002
A35: 2036 | B35: 0.037995779 | C35: 0.038956439 | D35: 0.045610629 | E35: 0.04064978 | F35: 0.019013858 | G35: 0.019013858 | M35: 2036 | N35: 322.3836 | O35: 322.3836 | P35: 322.3836 | Q35: 322.3836 | R35: 322.3836 | S35: 322.3836 | AA35: 2036 | AB35: 17.105674 | AC35: 23.843491 | AD35: 23.843491 | AE35: 23.843491 | AF35: 20.268257 | AG35: 20.268257 | AH35: 20.268257 | AI35: 23.959183 | AJ35: 23.545743
A36: 2037 | B36: 0.037117811 | C36: 0.037405737 | D36: 0.042491133 | E36: 0.038214655 | F36: 0.01871362 | G36: 0.01871362 | M36: 2037 | N36: 327.5008 | O36: 327.5008 | P36: 327.5008 | Q36: 327.5008 | R36: 327.5008 | S36: 327.5008 | AA36: 2037 | AB36: 17.377192 | AC36: 24.221959 | AD36: 24.221959 | AE36: 24.221959 | AF36: 20.589975 | AG36: 20.589975 | AH36: 20.589975 | AI36: 24.339488 | AJ36: 23.919485
A37: 2038 | B37: 0.036054354 | C37: 0.035649608 | D37: 0.03910056 | E37: 0.035546025 | F37: 0.018323819 | G37: 0.018323819 | M37: 2038 | N37: 331.3387 | O37: 331.3387 | P37: 331.3387 | Q37: 331.3387 | R37: 331.3387 | S37: 331.3387 | AA37: 2038 | AB37: 17.580831 | AC37: 24.50581 | AD37: 24.50581 | AE37: 24.50581 | AF37: 20.831264 | AG37: 20.831264 | AH37: 20.831264 | AI37: 24.624716 | AJ37: 24.199792
A38: 2039 | B38: 0.035089604 | C38: 0.033971813 | D38: 0.03575586 | E38: 0.032930411 | F38: 0.017988305 | G38: 0.017988305 | M38: 2039 | N38: 336.4559 | O38: 336.4559 | P38: 336.4559 | Q38: 336.4559 | R38: 336.4559 | S38: 336.4559 | AA38: 2039 | AB38: 17.85235 | AC38: 24.884278 | AD38: 24.884278 | AE38: 24.884278 | AF38: 21.152982 | AG38: 21.152982 | AH38: 21.152982 | AI38: 25.005021 | AJ38: 24.573534
... A44: 2045 | B44: 0.029857411 | C44: 0.027118644 | D44: 0.032853914 | E44: 0.029677348 | F44: 0.013842683 | G44: 0.013842683 | M44: 2045 | N44: 367.1591 | O44: 367.1591 | P44: 367.1591 | Q44: 367.1591 | R44: 367.1591 | S44: 367.1591 | AA44: 2045 | AB44: 19.481462 | AC44: 27.155087 | AD44: 27.155087 | AE44: 27.155087 | AF44: 23.083293 | AG44: 23.083293 | AH44: 23.083293 | AI44: 27.286848 | AJ44: 26.815986
A45: 2046 | B45: 0.029304678 | C45: 0.026854861 | D45: 0.032989962 | E45: 0.029735148 | F45: 0.013906119 | G45: 0.013906119 | M45: 2046 | N45: 372.2763 | O45: 372.2763 | P45: 372.2763 | Q45: 372.2763 | R45: 372.2763 | S45: 372.2763 | U45: Unit | V45: &/Tonne | AA45: 2046 | AB45: 19.75298 | AC45: 27.533555 | AD45: 27.533555 | AE45: 27.533555 | AF45: 23.405011 | AG45: 23.405011 | AH45: 23.405011 | AI45: 27.667152 | AJ45: 27.189728
A46: 2047 | B46: 0.028822683 | C46: 0.026663515 | D46: 0.033229423 | E46: 0.029884126 | F46: 0.014013337 | G46: 0.014013337 | M46: 2047 | N46: 378.6728 | O46: 378.6728 | P46: 378.6728 | Q46: 378.6728 | R46: 378.6728 | S46: 378.6728 | AA46: 2047 | AB46: 20.092379 | AC46: 28.00664 | AD46: 28.00664 | AE46: 28.00664 | AF46: 23.807159 | AG46: 23.807159 | AH46: 23.807159 | AI46: 28.142533 | AJ46: 27.656905
A47: 2048 | B47: 0.02821335 | C47: 0.026362242 | D47: 0.033346669 | E47: 0.02992114 | F47: 0.014069208 | G47: 0.014069208 | M47: 2048 | N47: 383.79 | O47: 383.79 | P47: 383.79 | Q47: 383.79 | R47: 383.79 | S47: 383.79 | AA47: 2048 | AB47: 20.363897 | AC47: 28.385108 | AD47: 28.385108 | AE47: 28.385108 | AF47: 24.128877 | AG47: 24.128877 | AH47: 24.128877 | AI47: 28.522837 | AJ47: 28.030647
A48: 2049 | B48: 0.027577381 | C48: 0.026043326 | D48: 0.033455067 | E48: 0.029948371 | F48: 0.014121519 | G48: 0.014121519 | M48: 2049 | N48: 388.9072 | O48: 388.9072 | P48: 388.9072 | Q48: 388.9072 | R48: 388.9072 | S48: 388.9072 | AA48: 2049 | AB48: 20.635416 | AC48: 28.763577 | AD48: 28.763577 | AE48: 28.763577 | AF48: 24.450596 | AG48: 24.450596 | AH48: 24.450596 | AI48: 28.903142 | AJ48: 28.404389
A49: 2050 | B49: 0.026914777 | C49: 0.025706768 | D49: 0.033554617 | E49: 0.029965821 | F49: 0.01417027 | G49: 0.01417027 | M49: 2050 | N49: 394.0244 | O49: 394.0244 | P49: 394.0244 | Q49: 394.0244 | R49: 394.0244 | S49: 394.0244 | AA49: 2050 | AB49: 20.906935 | AC49: 29.142045 | AD49: 29.142045 | AE49: 29.142045 | AF49: 24.772314 | AG49: 24.772314 | AH49: 24.772314 | AI49: 29.283446 | AJ49: 28.778131
A50: 2051 | B50: 0.026914777 | C50: 0.025706768 | D50: 0.033554617 | E50: 0.029965821 | F50: 0.01417027 | G50: 0.01417027 | AB50: 20.906935 | AC50: 29.142045 | AD50: 29.142045 | AE50: 29.142045 | AF50: 24.772314 | AG50: 24.772314 | AH50: 24.772314 | AI50: 29.283446 | AJ50: 28.778131
A51: 2052 | B51: 0.026914777 | C51: 0.025706768 | D51: 0.033554617 | E51: 0.029965821 | F51: 0.01417027 | G51: 0.01417027 | AB51: 20.906935 | AC51: 29.142045 | AD51: 29.142045 | AE51: 29.142045 | AF51: 24.772314 | AG51: 24.772314 | AH51: 24.772314 | AI51: 29.283446 | AJ51: 28.778131
A52: 2053 | B52: 0.026914777 | C52: 0.025706768 | D52: 0.033554617 | E52: 0.029965821 | F52: 0.01417027 | G52: 0.01417027 | AB52: 20.906935 | AC52: 29.142045 | AD52: 29.142045 | AE52: 29.142045 | AF52: 24.772314 | AG52: 24.772314 | AH52: 24.772314 | AI52: 29.283446 | AJ52: 28.778131
A53: 2054 | B53: 0.026914777 | C53: 0.025706768 | D53: 0.033554617 | E53: 0.029965821 | F53: 0.01417027 | G53: 0.01417027 | AB53: 20.906935 | AC53: 29.142045 | AD53: 29.142045 | AE53: 29.142045 | AF53: 24.772314 | AG53: 24.772314 | AH53: 24.772314 | AI53: 29.283446 | AJ53: 28.778131
A54: 2055 | B54: 0.026914777 | C54: 0.025706768 | D54: 0.033554617 | E54: 0.029965821 | F54: 0.01417027 | G54: 0.01417027 | AB54: 20.906935 | AC54: 29.142045 | AD54: 29.142045 | AE54: 29.142045 | AF54: 24.772314 | AG54: 24.772314 | AH54: 24.772314 | AI54: 29.283446 | AJ54: 28.778131
A55: 2056 | B55: 0.026914777 | C55: 0.025706768 | D55: 0.033554617 | E55: 0.029965821 | F55: 0.01417027 | G55: 0.01417027 | AB55: 20.906935 | AC55: 29.142045 | AD55: 29.142045 | AE55: 29.142045 | AF55: 24.772314 | AG55: 24.772314 | AH55: 24.772314 | AI55: 29.283446 | AJ55: 28.778131
A56: 2057 | B56: 0.026914777 | C56: 0.025706768 | D56: 0.033554617 | E56: 0.029965821 | F56: 0.01417027 | G56: 0.01417027 | AB56: 20.906935 | AC56: 29.142045 | AD56: 29.142045 | AE56: 29.142045 | AF56: 24.772314 | AG56: 24.772314 | AH56: 24.772314 | AI56: 29.283446 | AJ56: 28.778131
A57: 2058 | B57: 0.026914777 | C57: 0.025706768 | D57: 0.033554617 | E57: 0.029965821 | F57: 0.01417027 | G57: 0.01417027 | AB57: 20.906935 | AC57: 29.142045 | AD57: 29.142045 | AE57: 29.142045 | AF57: 24.772314 | AG57: 24.772314 | AH57: 24.772314 | AI57: 29.283446 | AJ57: 28.778131
A58: 2059 | B58: 0.026914777 | C58: 0.025706768 | D58: 0.033554617 | E58: 0.029965821 | F58: 0.01417027 | G58: 0.01417027 | AB58: 20.906935 | AC58: 29.142045 | AD58: 29.142045 | AE58: 29.142045 | AF58: 24.772314 | AG58: 24.772314 | AH58: 24.772314 | AI58: 29.283446 | AJ58: 28.778131
A59: 2060 | B59: 0.026914777 | C59: 0.025706768 | D59: 0.033554617 | E59: 0.029965821 | F59: 0.01417027 | G59: 0.01417027 | AB59: 20.906935 | AC59: 29.142045 | AD59: 29.142045 | AE59: 29.142045 | AF59: 24.772314 | AG59: 24.772314 | AH59: 24.772314 | AI59: 29.283446 | AJ59: 28.778131
A60: 2061 | B60: 0.026914777 | C60: 0.025706768 | D60: 0.033554617 | E60: 0.029965821 | F60: 0.01417027 | G60: 0.01417027 | AB60: 20.906935 | AC60: 29.142045 | AD60: 29.142045 | AE60: 29.142045 | AF60: 24.772314 | AG60: 24.772314 | AH60: 24.772314 | AI60: 29.283446 | AJ60: 28.778131
A61: 2062 | B61: 0.026914777 | C61: 0.025706768 | D61: 0.033554617 | E61: 0.029965821 | F61: 0.01417027 | G61: 0.01417027 | AB61: 20.906935 | AC61: 29.142045 | AD61: 29.142045 | AE61: 29.142045 | AF61: 24.772314 | AG61: 24.772314 | AH61: 24.772314 | AI61: 29.283446 | AJ61: 28.778131
... A74: 2075 | B74: 0.026914777 | C74: 0.025706768 | D74: 0.033554617 | E74: 0.029965821 | F74: 0.01417027 | G74: 0.01417027 | AB74: 20.906935 | AC74: 29.142045 | AD74: 29.142045 | AE74: 29.142045 | AF74: 24.772314 | AG74: 24.772314 | AH74: 24.772314 | AI74: 29.283446 | AJ74: 28.778131
B76: Nox | G76: U.S. Energy Information Administration - EIA - Independent Statistics and Analysis
B77: USER DEFINED | N77: USER DEFINED | AA77: Emissions Factors (tonnes/MMBtu) | AB77: 1e-07 | AC77: 6e-07 | AD77: 6e-07 | AE77: 6e-07 | AF77: 6e-07 | AG77: 6e-07 | AH77: 6e-07 | AI77: 6e-07 | AJ77: 6e-07
B78: ELECTRIC EXTERNALITIES without losses (at gen) | N78: ELECTRIC EXTERNALITIES without losses (at gen) | AB78: 1 | AC78: 2 | AD78: 3 | AE78: 4 | AF78: 5 | AG78: 6 | AH78: 7 | AI78: 8 | AJ78: 9
B79: Summer On-Peak | C79: Summer Off-Peak | D79: Winter On-Peak | E79: Winter Off-Peak | F79: Shoulder On-Peak | G79: Shoulder Off-Peak | N79: Summer On-Peak | O79: Summer Off-Peak | P79: Winter On-Peak | Q79: Winter Off-Peak | R79: Shoulder On-Peak | S79: Shoulder Off-Peak | AB79: Natural Gas | AC79: Res Fuel Oil | AD79: Com Fuel Oil | AE79: Ind Fuel Oil | AF79: Res Propane | AG79: Com Propane | AH79: Ind Propane | AI79: Diesel, Transportation | AJ79: Gasoline, Transportation
AB81: Natural Gas | AC81: Oil | AD81: Oil | AE81: Oil | AF81: Propane | AG81: Propane | AH81: Propane | AI81: Oil | AJ81: Oil
B82: $/kWh | C82: $/kWh | D82: $/kWh | E82: $/kWh | F82: $/kWh | G82: $/kWh | N82: $/tonne | O82: $/tonne | P82: $/tonne | Q82: $/tonne | R82: $/tonne | S82: $/tonne | AB82: $/MMBtu | AC82: $/MMBtu | AD82: $/MMBtu | AE82: $/MMBtu | AF82: $/MMBtu | AG82: $/MMBtu | AH82: $/MMBtu | AI82: $/MMBtu | AJ82: $/MMBtu
A83: 2020 | M83: 2020
A84: 2021 | M84: 2021
A85: 2022 | M85: 2022
A86: 2023 | M86: 2023
A87: 2024 | M87: 2024
A88: 2025 | B88: 0.17 | C88: 0.18 | D88: 0.22 | E88: 0.23 | F88: 0.1 | G88: 0.1 | M88: 2025
A89: 2026 | B89: 0.0001487 | C89: 0.0001577 | D89: 0.0001934 | E89: 0.0001991 | F89: 9.035e-05 | G89: 9.035e-05 | M89: 2026 | N89: 78666.72 | O89: 78666.72 | P89: 78666.72 | Q89: 78666.716 | R89: 78666.72 | S89: 78666.72 | AA89: 2026 | AB89: 0.007866672 | AC89: 0.047200029 | AD89: 0.0472 | AE89: 0.0472 | AF89: 0.047200029 | AG89: 0.0472 | AH89: 0.0472 | AI89: 0.047200029 | AJ89: 0.047200029
A90: 2027 | B90: 0.000162815 | C90: 0.000174535 | D90: 0.000208679 | E90: 0.000210982 | F90: 9.71395e-05 | G90: 9.71395e-05 | M90: 2027 | N90: 80235.14 | O90: 80235.14 | P90: 80235.14 | Q90: 80235.137 | R90: 80235.14 | S90: 80235.14 | U90: EPA Report on the Social Cost of Greenhouse Gases: Estimates Incorporating Recent Scientific Advances | AA90: 2027 | AB90: 0.008023514 | AC90: 0.048141082 | AD90: 0.0481411 | AE90: 0.0481411 | AF90: 0.048141082 | AG90: 0.0481411 | AH90: 0.0481411 | AI90: 0.048141082 | AJ90: 0.048141082
A91: 2028 | B91: 0.000177331 | C91: 0.000191884 | D91: 0.000224361 | E91: 0.000223182 | F91: 0.000104129 | G91: 0.000104129 | M91: 2028 | N91: 81803.56 | O91: 81803.56 | P91: 81803.56 | Q91: 81803.559 | R91: 81803.56 | S91: 81803.56 | AA91: 2028 | AB91: 0.008180356 | AC91: 0.049082136 | AD91: 0.0490821 | AE91: 0.0490821 | AF91: 0.049082136 | AG91: 0.0490821 | AH91: 0.0490821 | AI91: 0.049082136 | AJ91: 0.049082136
A92: 2029 | B92: 0.000192277 | C92: 0.000209763 | D92: 0.000240484 | E92: 0.000235689 | F92: 0.000111312 | G92: 0.000111312 | M92: 2029 | N92: 83370.7 | O92: 83370.7 | P92: 83370.7 | Q92: 83370.702 | R92: 83370.7 | S92: 83370.7 | AA92: 2029 | AB92: 0.00833707 | AC92: 0.050022421 | AD92: 0.0500224 | AE92: 0.0500224 | AF92: 0.050022421 | AG92: 0.0500224 | AH92: 0.0500224 | AI92: 0.050022421 | AJ92: 0.050022421
A93: 2030 | B93: 0.000207662 | C93: 0.00022818 | D93: 0.000257055 | E93: 0.000248508 | F93: 0.000118692 | G93: 0.000118692 | M93: 2030 | N93: 84939.12 | O93: 84939.12 | P93: 84939.12 | Q93: 84939.124 | R93: 84939.12 | S93: 84939.12 | AA93: 2030 | AB93: 0.008493912 | AC93: 0.050963474 | AD93: 0.0509635 | AE93: 0.0509635 | AF93: 0.050963474 | AG93: 0.0509635 | AH93: 0.0509635 | AI93: 0.050963474 | AJ93: 0.050963474
A94: 2031 | B94: 0.000176135 | C94: 0.000193376 | D94: 0.000217957 | E94: 0.000210054 | F94: 9.96742e-05 | G94: 9.96742e-05 | M94: 2031 | N94: 86538.25 | O94: 86538.25 | P94: 86538.25 | Q94: 86538.249 | R94: 86538.25 | S94: 86538.25 | AA94: 2031 | AB94: 0.008653825 | AC94: 0.051922949 | AD94: 0.0519229 | AE94: 0.0519229 | AF94: 0.051922949 | AG94: 0.0519229 | AH94: 0.0519229 | AI94: 0.051922949 | AJ94: 0.051922949
A95: 2032 | B95: 0.000143298 | C95: 0.000157128 | D95: 0.000177235 | E95: 0.000170006 | F95: 7.98714e-05 | G95: 7.98714e-05 | M95: 2032 | N95: 88137.37 | O95: 88137.37 | P95: 88137.37 | Q95: 88137.374 | R95: 88137.37 | S95: 88137.37 | AA95: 2032 | AB95: 0.008813737 | AC95: 0.052882424 | AD95: 0.0528824 | AE95: 0.0528824 | AF95: 0.052882424 | AG95: 0.0528824 | AH95: 0.0528824 | AI95: 0.052882424 | AJ95: 0.052882424
A96: 2033 | B96: 0.000109151 | C96: 0.000119434 | D96: 0.000134888 | E96: 0.000128363 | F96: 5.92832e-05 | G96: 5.92832e-05 | M96: 2033 | N96: 89736.5 | O96: 89736.5 | P96: 89736.5 | Q96: 89736.499 | R96: 89736.5 | S96: 89736.5 | AA96: 2033 | AB96: 0.00897365 | AC96: 0.053841899 | AD96: 0.0538419 | AE96: 0.0538419 | AF96: 0.053841899 | AG96: 0.0538419 | AH96: 0.0538419 | AI96: 0.053841899 | AJ96: 0.053841899
A97: 2034 | B97: 7.36944e-05 | C97: 8.02945e-05 | D97: 9.09172e-05 | E97: 8.51259e-05 | F97: 3.7909e-05 | G97: 3.7909e-05 | M97: 2034 | N97: 91334.34 | O97: 91334.34 | P97: 91334.34 | Q97: 91334.344 | R97: 91334.34 | S97: 91334.34 | AA97: 2034 | AB97: 0.009133434 | AC97: 0.054800607 | AD97: 0.0548006 | AE97: 0.0548006 | AF97: 0.054800607 | AG97: 0.0548006 | AH97: 0.0548006 | AI97: 0.054800607 | AJ97: 0.054800607
A98: 2035 | B98: 3.69293e-05 | C98: 3.97116e-05 | D98: 4.5324e-05 | E98: 4.02962e-05 | F98: 1.57502e-05 | G98: 1.57502e-05 | M98: 2035 | N98: 92933.47 | O98: 92933.47 | P98: 92933.47 | Q98: 92933.469 | R98: 92933.47 | S98: 92933.47 | AA98: 2035 | AB98: 0.009293347 | AC98: 0.055760082 | AD98: 0.0557601 | AE98: 0.0557601 | AF98: 0.055760082 | AG98: 0.0557601 | AH98: 0.0557601 | AI98: 0.055760082 | AJ98: 0.055760082
A99: 2036 | B99: 3.47577e-05 | C99: 3.6895e-05 | D99: 4.13256e-05 | E99: 3.6944e-05 | F99: 1.49592e-05 | G99: 1.49592e-05 | M99: 2036 | N99: 94532.59 | O99: 94532.59 | P99: 94532.59 | Q99: 94532.594 | R99: 94532.59 | S99: 94532.59 | AA99: 2036 | AB99: 0.009453259 | AC99: 0.056719557 | AD99: 0.0567196 | AE99: 0.0567196 | AF99: 0.056719557 | AG99: 0.0567196 | AH99: 0.0567196 | AI99: 0.056719557 | AJ99: 0.056719557
A100: 2037 | B100: 3.24911e-05 | C100: 3.39599e-05 | D100: 3.71655e-05 | E100: 3.3455e-05 | F100: 1.41322e-05 | G100: 1.41322e-05 | M100: 2037 | N100: 96131.72 | O100: 96131.72 | P100: 96131.72 | Q100: 96131.719 | R100: 96131.72 | S100: 96131.72 | AA100: 2037 | AB100: 0.009613172 | AC100: 0.057679032 | AD100: 0.057679 | AE100: 0.057679 | AF100: 0.057679032 | AG100: 0.057679 | AH100: 0.057679 | AI100: 0.057679032 | AJ100: 0.057679032
A101: 2038 | B101: 3.01296e-05 | C101: 3.09065e-05 | D101: 3.28438e-05 | E101: 2.98291e-05 | F101: 1.32692e-05 | G101: 1.32692e-05 | M101: 2038 | N101: 97730.84 | O101: 97730.84 | P101: 97730.84 | Q101: 97730.844 | R101: 97730.84 | S101: 97730.84 | AA101: 2038 | AB101: 0.009773084 | AC101: 0.058638507 | AD101: 0.0586385 | AE101: 0.0586385 | AF101: 0.058638507 | AG101: 0.0586385 | AH101: 0.0586385 | AI101: 0.058638507 | AJ101: 0.058638507
A102: 2039 | B102: 2.7673e-05 | C102: 2.77346e-05 | D102: 2.83604e-05 | E102: 2.60664e-05 | F102: 1.23703e-05 | G102: 1.23703e-05 | M102: 2039 | N102: 99329.97 | O102: 99329.97 | P102: 99329.97 | Q102: 99329.969 | R102: 99329.97 | S102: 99329.97 | AA102: 2039 | AB102: 0.009932997 | AC102: 0.059597982 | AD102: 0.059598 | AE102: 0.059598 | AF102: 0.059597982 | AG102: 0.059598 | AH102: 0.059598 | AI102: 0.059597982 | AJ102: 0.059597982
... A108: 2045 | B108: 2.10157e-05 | C108: 1.95412e-05 | D108: 2.54676e-05 | E108: 2.20879e-05 | F108: 9.1173e-06 | G108: 9.1173e-06 | M108: 2045 | N108: 109949.4 | O108: 109949.4 | P108: 109949.4 | Q108: 109949.44 | R108: 109949.4 | S108: 109949.4 | AA108: 2045 | AB108: 0.010994944 | AC108: 0.065969663 | AD108: 0.0659697 | AE108: 0.0659697 | AF108: 0.065969663 | AG108: 0.0659697 | AH108: 0.0659697 | AI108: 0.065969663 | AJ108: 0.065969663
A109: 2046 | B109: 2.04922e-05 | C109: 1.9178e-05 | D109: 2.5058e-05 | E109: 2.18793e-05 | F109: 9.1438e-06 | G109: 9.1438e-06 | M109: 2046 | N109: 111753.3 | O109: 111753.3 | P109: 111753.3 | Q109: 111753.25 | R109: 111753.3 | S109: 111753.3 | U109: Unit | V109: &/Tonne | AA109: 2046 | AB109: 0.011175325 | AC109: 0.067051951 | AD109: 0.067052 | AE109: 0.067052 | AF109: 0.067051951 | AG109: 0.067052 | AH109: 0.067052 | AI109: 0.067051951 | AJ109: 0.067051951
A110: 2047 | B110: 1.99406e-05 | C110: 1.87927e-05 | D110: 2.46217e-05 | E110: 2.16523e-05 | F110: 9.16633e-06 | G110: 9.16633e-06 | M110: 2047 | N110: 113557.1 | O110: 113557.1 | P110: 113557.1 | Q110: 113557.06 | R110: 113557.1 | S110: 113557.1 | AA110: 2047 | AB110: 0.011355706 | AC110: 0.068134239 | AD110: 0.0681342 | AE110: 0.0681342 | AF110: 0.068134239 | AG110: 0.0681342 | AH110: 0.0681342 | AI110: 0.068134239 | AJ110: 0.068134239
A111: 2048 | B111: 1.93612e-05 | C111: 1.83855e-05 | D111: 2.4159e-05 | E111: 2.14071e-05 | F111: 9.18499e-06 | G111: 9.18499e-06 | M111: 2048 | N111: 115362.2 | O111: 115362.2 | P111: 115362.2 | Q111: 115362.16 | R111: 115362.2 | S111: 115362.2 | AA111: 2048 | AB111: 0.011536216 | AC111: 0.069217294 | AD111: 0.0692173 | AE111: 0.0692173 | AF111: 0.069217294 | AG111: 0.0692173 | AH111: 0.0692173 | AI111: 0.069217294 | AJ111: 0.069217294
A112: 2049 | B112: 1.87535e-05 | C112: 1.79561e-05 | D112: 2.36693e-05 | E112: 2.11432e-05 | F112: 9.19957e-06 | G112: 9.19957e-06 | M112: 2049 | N112: 117166 | O112: 117166 | P112: 117166 | Q112: 117165.97 | R112: 117166 | S112: 117166 | AA112: 2049 | AB112: 0.011716597 | AC112: 0.070299582 | AD112: 0.0702996 | AE112: 0.0702996 | AF112: 0.070299582 | AG112: 0.0702996 | AH112: 0.0702996 | AI112: 0.070299582 | AJ112: 0.070299582
A113: 2050 | B113: 1.81179e-05 | C113: 1.75046e-05 | D113: 2.31529e-05 | E113: 2.08609e-05 | F113: 9.21018e-06 | G113: 9.21018e-06 | M113: 2050 | N113: 118969.8 | O113: 118969.8 | P113: 118969.8 | Q113: 118969.78 | R113: 118969.8 | S113: 118969.8 | AA113: 2050 | AB113: 0.011896978 | AC113: 0.07138187 | AD113: 0.0713819 | AE113: 0.0713819 | AF113: 0.07138187 | AG113: 0.0713819 | AH113: 0.0713819 | AI113: 0.07138187 | AJ113: 0.07138187
A114: 2051 | B114: 1.81179e-05 | C114: 1.75046e-05 | D114: 2.31529e-05 | E114: 2.08609e-05 | F114: 9.21018e-06 | G114: 9.21018e-06 | AB114: 0.011896978 | AC114: 0.07138187 | AD114: 0.0713819 | AE114: 0.0713819 | AF114: 0.07138187 | AG114: 0.0713819 | AH114: 0.0713819 | AI114: 0.07138187 | AJ114: 0.07138187
A115: 2052 | B115: 1.81179e-05 | C115: 1.75046e-05 | D115: 2.31529e-05 | E115: 2.08609e-05 | F115: 9.21018e-06 | G115: 9.21018e-06 | AB115: 0.011896978 | AC115: 0.07138187 | AD115: 0.0713819 | AE115: 0.0713819 | AF115: 0.07138187 | AG115: 0.0713819 | AH115: 0.0713819 | AI115: 0.07138187 | AJ115: 0.07138187
A116: 2053 | B116: 1.81179e-05 | C116: 1.75046e-05 | D116: 2.31529e-05 | E116: 2.08609e-05 | F116: 9.21018e-06 | G116: 9.21018e-06 | AB116: 0.011896978 | AC116: 0.07138187 | AD116: 0.0713819 | AE116: 0.0713819 | AF116: 0.07138187 | AG116: 0.0713819 | AH116: 0.0713819 | AI116: 0.07138187 | AJ116: 0.07138187
A117: 2054 | B117: 1.81179e-05 | C117: 1.75046e-05 | D117: 2.31529e-05 | E117: 2.08609e-05 | F117: 9.21018e-06 | G117: 9.21018e-06 | AB117: 0.011896978 | AC117: 0.07138187 | AD117: 0.0713819 | AE117: 0.0713819 | AF117: 0.07138187 | AG117: 0.0713819 | AH117: 0.0713819 | AI117: 0.07138187 | AJ117: 0.07138187
A118: 2055 | B118: 1.81179e-05 | C118: 1.75046e-05 | D118: 2.31529e-05 | E118: 2.08609e-05 | F118: 9.21018e-06 | G118: 9.21018e-06 | AB118: 0.011896978 | AC118: 0.07138187 | AD118: 0.0713819 | AE118: 0.0713819 | AF118: 0.07138187 | AG118: 0.0713819 | AH118: 0.0713819 | AI118: 0.07138187 | AJ118: 0.07138187
A119: 2056 | B119: 1.81179e-05 | C119: 1.75046e-05 | D119: 2.31529e-05 | E119: 2.08609e-05 | F119: 9.21018e-06 | G119: 9.21018e-06 | AB119: 0.011896978 | AC119: 0.07138187 | AD119: 0.0713819 | AE119: 0.0713819 | AF119: 0.07138187 | AG119: 0.0713819 | AH119: 0.0713819 | AI119: 0.07138187 | AJ119: 0.07138187
A120: 2057 | B120: 1.81179e-05 | C120: 1.75046e-05 | D120: 2.31529e-05 | E120: 2.08609e-05 | F120: 9.21018e-06 | G120: 9.21018e-06 | AB120: 0.011896978 | AC120: 0.07138187 | AD120: 0.0713819 | AE120: 0.0713819 | AF120: 0.07138187 | AG120: 0.0713819 | AH120: 0.0713819 | AI120: 0.07138187 | AJ120: 0.07138187
A121: 2058 | B121: 1.81179e-05 | C121: 1.75046e-05 | D121: 2.31529e-05 | E121: 2.08609e-05 | F121: 9.21018e-06 | G121: 9.21018e-06 | AB121: 0.011896978 | AC121: 0.07138187 | AD121: 0.0713819 | AE121: 0.0713819 | AF121: 0.07138187 | AG121: 0.0713819 | AH121: 0.0713819 | AI121: 0.07138187 | AJ121: 0.07138187
A122: 2059 | B122: 1.81179e-05 | C122: 1.75046e-05 | D122: 2.31529e-05 | E122: 2.08609e-05 | F122: 9.21018e-06 | G122: 9.21018e-06 | AB122: 0.011896978 | AC122: 0.07138187 | AD122: 0.0713819 | AE122: 0.0713819 | AF122: 0.07138187 | AG122: 0.0713819 | AH122: 0.0713819 | AI122: 0.07138187 | AJ122: 0.07138187
A123: 2060 | B123: 1.81179e-05 | C123: 1.75046e-05 | D123: 2.31529e-05 | E123: 2.08609e-05 | F123: 9.21018e-06 | G123: 9.21018e-06 | AB123: 0.011896978 | AC123: 0.07138187 | AD123: 0.0713819 | AE123: 0.0713819 | AF123: 0.07138187 | AG123: 0.0713819 | AH123: 0.0713819 | AI123: 0.07138187 | AJ123: 0.07138187
A124: 2061 | B124: 1.81179e-05 | C124: 1.75046e-05 | D124: 2.31529e-05 | E124: 2.08609e-05 | F124: 9.21018e-06 | G124: 9.21018e-06 | AB124: 0.011896978 | AC124: 0.07138187 | AD124: 0.0713819 | AE124: 0.0713819 | AF124: 0.07138187 | AG124: 0.0713819 | AH124: 0.0713819 | AI124: 0.07138187 | AJ124: 0.07138187
A125: 2062 | B125: 1.81179e-05 | C125: 1.75046e-05 | D125: 2.31529e-05 | E125: 2.08609e-05 | F125: 9.21018e-06 | G125: 9.21018e-06 | AB125: 0.011896978 | AC125: 0.07138187 | AD125: 0.0713819 | AE125: 0.0713819 | AF125: 0.07138187 | AG125: 0.0713819 | AH125: 0.0713819 | AI125: 0.07138187 | AJ125: 0.07138187
... A138: 2075 | B138: 1.81179e-05 | C138: 1.75046e-05 | D138: 2.31529e-05 | E138: 2.08609e-05 | F138: 9.21018e-06 | G138: 9.21018e-06 | AB138: 0.011896978 | AC138: 0.07138187 | AD138: 0.0713819 | AE138: 0.0713819 | AF138: 0.07138187 | AG138: 0.0713819 | AH138: 0.0713819 | AI138: 0.07138187 | AJ138: 0.07138187
...
