Workbook

Sheet Retail_Rates
A1: Year | B1: =LOWER(_xlfn.CONCAT(Sheet2!$AO15,"_", Sheet2!AO16,"_", Sheet2!AO19)) -> electricity_res_$/kwh | C1: =LOWER(_xlfn.CONCAT(Sheet2!$AO15,"_", Sheet2!AP16,"_", Sheet2!AP19)) -> electricity_commercial_$/kwh | D1: =LOWER(_xlfn.CONCAT(Sheet2!$AO15,"_", Sheet2!AQ16,"_", Sheet2!AQ19)) -> electricity_industrial_$/kwh | E1: =LOWER(_xlfn.CONCAT(Sheet2!$AT15,"_", Sheet2!AT16,"_", Sheet2!AT19)) -> natural gas_res_$/mmbtu | F1: =LOWER(_xlfn.CONCAT(Sheet2!$AT15,"_", Sheet2!AU16,"_", Sheet2!AU19)) -> natural gas_commercial_$/mmbtu | G1: =LOWER(_xlfn.CONCAT(Sheet2!$AT15,"_", Sheet2!AV16,"_", Sheet2!AV19)) -> natural gas_industrial_$/mmbtu | H1: =LOWER(_xlfn.CONCAT(Sheet2!$AY15,"_", Sheet2!AY16,"_", Sheet2!AY19)) -> heating oil_res_$/mmbtu | I1: =LOWER(_xlfn.CONCAT(Sheet2!$AY15,"_", Sheet2!AZ16,"_", Sheet2!AZ19)) -> heating oil_commercial_$/mmbtu | J1: =LOWER(_xlfn.CONCAT(Sheet2!$AY15,"_", Sheet2!BA16,"_", Sheet2!BA19)) -> heating oil_industrial_$/mmbtu
A2: =Sheet2!A20 -> 2026 | B2: =Sheet2!AO20 -> 0.2 | C2: =Sheet2!AP20 -> 0.14 | D2: =Sheet2!AQ20 -> 0.08 | E2: =Sheet2!AT20 -> 11.26 | F2: =Sheet2!AU20 -> 9.77 | G2: =Sheet2!AV20 -> 7.91 | H2: =Sheet2!AY20 -> 24.68 | I2: =Sheet2!AZ20 -> 18.71 | J2: =Sheet2!BA20 -> 18.71
A3: =Sheet2!A21 -> 2027 | B3: =Sheet2!AO21 -> 0.21 | C3: =Sheet2!AP21 -> 0.14 | D3: =Sheet2!AQ21 -> 0.08 | E3: =Sheet2!AT21 -> 10.72 | F3: =Sheet2!AU21 -> 9.96 | G3: =Sheet2!AV21 -> 7.69 | H3: =Sheet2!AY21 -> 25 | I3: =Sheet2!AZ21 -> 18.24 | J3: =Sheet2!BA21 -> 18.19
A4: =Sheet2!A22 -> 2028 | B4: =Sheet2!AO22 -> 0.21 | C4: =Sheet2!AP22 -> 0.14 | D4: =Sheet2!AQ22 -> 0.08 | E4: =Sheet2!AT22 -> 10.38 | F4: =Sheet2!AU22 -> 10.34 | G4: =Sheet2!AV22 -> 7.76 | H4: =Sheet2!AY22 -> 25.57 | I4: =Sheet2!AZ22 -> 17.97 | J4: =Sheet2!BA22 -> 17.87
A5: =Sheet2!A23 -> 2029 | B5: =Sheet2!AO23 -> 0.22 | C5: =Sheet2!AP23 -> 0.14 | D5: =Sheet2!AQ23 -> 0.08 | E5: =Sheet2!AT23 -> 10.19 | F5: =Sheet2!AU23 -> 10.84 | G5: =Sheet2!AV23 -> 7.94 | H5: =Sheet2!AY23 -> 26.19 | I5: =Sheet2!AZ23 -> 17.72 | J5: =Sheet2!BA23 -> 17.57
A6: =Sheet2!A24 -> 2030 | B6: =Sheet2!AO24 -> 0.22 | C6: =Sheet2!AP24 -> 0.15 | D6: =Sheet2!AQ24 -> 0.08 | E6: =Sheet2!AT24 -> 9.98 | F6: =Sheet2!AU24 -> 11.31 | G6: =Sheet2!AV24 -> 8.15 | H6: =Sheet2!AY24 -> 26.88 | I6: =Sheet2!AZ24 -> 17.5 | J6: =Sheet2!BA24 -> 17.3
A7: =Sheet2!A25 -> 2031 | B7: =Sheet2!AO25 -> 0.22 | C7: =Sheet2!AP25 -> 0.15 | D7: =Sheet2!AQ25 -> 0.08 | E7: =Sheet2!AT25 -> 10.2 | F7: =Sheet2!AU25 -> 11.51 | G7: =Sheet2!AV25 -> 8.37 | H7: =Sheet2!AY25 -> 26.98 | I7: =Sheet2!AZ25 -> 17.56 | J7: =Sheet2!BA25 -> 17.36
A8: =Sheet2!A26 -> 2032 | B8: =Sheet2!AO26 -> 0.21 | C8: =Sheet2!AP26 -> 0.14 | D8: =Sheet2!AQ26 -> 0.08 | E8: =Sheet2!AT26 -> 10.71 | F8: =Sheet2!AU26 -> 12.01 | G8: =Sheet2!AV26 -> 9.1 | H8: =Sheet2!AY26 -> 26.83 | I8: =Sheet2!AZ26 -> 17.49 | J8: =Sheet2!BA26 -> 17.3
A9: =Sheet2!A27 -> 2033 | B9: =Sheet2!AO27 -> 0.22 | C9: =Sheet2!AP27 -> 0.14 | D9: =Sheet2!AQ27 -> 0.08 | E9: =Sheet2!AT27 -> 11.18 | F9: =Sheet2!AU27 -> 12.46 | G9: =Sheet2!AV27 -> 9.66 | H9: =Sheet2!AY27 -> 27.26 | I9: =Sheet2!AZ27 -> 17.79 | J9: =Sheet2!BA27 -> 17.6
A10: =Sheet2!A28 -> 2034 | B10: =Sheet2!AO28 -> 0.22 | C10: =Sheet2!AP28 -> 0.14 | D10: =Sheet2!AQ28 -> 0.08 | E10: =Sheet2!AT28 -> 11.49 | F10: =Sheet2!AU28 -> 12.72 | G10: =Sheet2!AV28 -> 9.95 | H10: =Sheet2!AY28 -> 27.43 | I10: =Sheet2!AZ28 -> 17.92 | J10: =Sheet2!BA28 -> 17.73
A11: =Sheet2!A29 -> 2035 | B11: =Sheet2!AO29 -> 0.22 | C11: =Sheet2!AP29 -> 0.15 | D11: =Sheet2!AQ29 -> 0.08 | E11: =Sheet2!AT29 -> 11.66 | F11: =Sheet2!AU29 -> 12.84 | G11: =Sheet2!AV29 -> 10.06 | H11: =Sheet2!AY29 -> 27.65 | I11: =Sheet2!AZ29 -> 18.13 | J11: =Sheet2!BA29 -> 17.94
A12: =Sheet2!A30 -> 2036 | B12: =Sheet2!AO30 -> 0.21 | C12: =Sheet2!AP30 -> 0.14 | D12: =Sheet2!AQ30 -> 0.08 | E12: =Sheet2!AT30 -> 11.71 | F12: =Sheet2!AU30 -> 12.83 | G12: =Sheet2!AV30 -> 10.02 | H12: =Sheet2!AY30 -> 27.69 | I12: =Sheet2!AZ30 -> 18.21 | J12: =Sheet2!BA30 -> 18.03
A13: =Sheet2!A31 -> 2037 | B13: =Sheet2!AO31 -> 0.22 | C13: =Sheet2!AP31 -> 0.14 | D13: =Sheet2!AQ31 -> 0.08 | E13: =Sheet2!AT31 -> 11.68 | F13: =Sheet2!AU31 -> 12.75 | G13: =Sheet2!AV31 -> 9.87 | H13: =Sheet2!AY31 -> 27.91 | I13: =Sheet2!AZ31 -> 18.38 | J13: =Sheet2!BA31 -> 18.21
... A26: =Sheet2!A44 -> 2050 | B26: =Sheet2!AO44 -> 0.25 | C26: =Sheet2!AP44 -> 0.17 | D26: =Sheet2!AQ44 -> 0.09 | E26: =Sheet2!AT44 -> 12.35 | F26: =Sheet2!AU44 -> 12.92 | G26: =Sheet2!AV44 -> 9.61 | H26: =Sheet2!AY44 -> 31.29 | I26: =Sheet2!AZ44 -> 20.55 | J26: =Sheet2!BA44 -> 20.34

Sheet Sheet2
A1: Avoided Costs & Fuel Prices | E1: All Avoided Costs must be in Year 2026$ | M1: END-USE FUEL COSTS
B3: LINE LOSS FACTORS (% of meter) | M3: RETAIL FUEL COST ADDERS ($/MMBtu) | AI3: EMISSIONS IMPACTS | AM3: $/tonne CO2
A4: Sectors | B4: Summer On-Peak | C4: Summer Off-Peak | D4: Winter On-Peak | E4: Winter Off-Peak | F4: Shoulder | H4: Summer Gener. Capacity | J4: Summer T&D | M4: Sectors | N4: Natural Gas | O4: 0 | P4: 0 | Q4: 0 | R4: 0 | S4: 0 | AI4: CO2 | AJ4: NOx | AK4: CH4 | AL4: Equivalent CO2 Externalities
A5: Res | B5: 0.1 | C5: 0.1 | D5: 0.1 | E5: 0.1 | F5: 0.1 | H5: 0.241 | J5: 0.241 | M5: Res | AH5: Electric (tonne/MWh at gen) | AI5: 0 | AJ5: 0 | AK5: 0 | AL5: $- | AM5: $/kWh | AO5: 1 tonne = 1 "metric ton"
A6: Small C&I | B6: 0.0895 | C6: 0.0895 | D6: 0.0895 | E6: 0.0895 | F6: 0.0895 | H6: 0.241 | J6: 0.241 | M6: Small C&I | AH6: Nat Gas (tonne/MMBtu) | AI6: 0.05306 | AJ6: 1e-07 | AK6: 1e-06 | AL6: $- | AM6: $/MMBtu | AO6: 1 US short ton = 2000 lbs
A7: Large C&I | B7: 0.0895 | C7: 0.0895 | D7: 0.0895 | E7: 0.0895 | F7: 0.0895 | H7: 0.241 | J7: 0.241 | M7: Large C&I | AH7: Oil (tonne/MMBtu) | AI7: 0.07396 | AJ7: 6e-07 | AK7: 3e-06 | AL7: $- | AM7: $/MMBtu | AO7: 1.102 | AP7: US short ton/tonne
AO8: 0.00892 | AP8: tonne CO2/gallon of gas | AS8: http://www.epa.gov/cleanenergy/energy-resources/refs.html
AL9: $- | AM9: $/gallon of gas equivalent for cost of CO2 (combustion CO2 only)
N11: USER DEFINED END-USE EXTERNALITIES ($/MMBtu)
N12: 0
B14: ELECTRIC AVOIDED COSTS w/o losses (at gen) | G14: 1 | H14: Electric Avoided Costs Multiplier | N14: 1 | O14: End-use Fuel Costs Multiplier | AE14: OTHER RESOURCE | AH14: USER DEFINED | AO14: RETAIL PRICES BY SECTOR (2026$) - For the Participant Test | BE14: ELEC SALES & RIM INPUTS
B15: kWh1 | C15: kWh2 | D15: kWh3 | E15: kWh4 | F15: kWh5 | G15: kWh6 | H15: kW1 | I15: kW2 | J15: kW3 | K15: kW4 | N15: 1 | O15: 2 | P15: 3 | Q15: 4 | R15: 5 | S15: 6 | T15: 7 | U15: 8 | V15: 9 | W15: 10 | X15: 11 | Y15: 12 | Z15: 13 | AA15: 14 | AB15: 15 | AC15: 16 | AE15: AVOIDED COSTS | AH15: ELECTRIC EXTERNALITIES without losses (at gen) | AO15: ELECTRICITY | AT15: NATURAL GAS | AY15: HEATING OIL | BE15: Base Case
A16: Period/ | B16: Summer On-Peak | C16: Summer Off-Peak | D16: Winter On-Peak | E16: Winter Off-Peak | F16: Shoulder | H16: Summer Gener. Capacity | I16: winter_gener_capacity_usdperkW-yr | J16: Summer T&D | K16: winter_td_usdperkW-yr | N16: Natural Gas | O16: Res Fuel Oil | P16: Com Fuel Oil | Q16: Ind Fuel Oil | R16: Res Propane | S16: Com Propane | T16: Ind Propane | U16: Diesel, Transportation | V16: Gasoline, Transportation | AE16: Water | AH16: Summer On-Peak | AI16: Summer Off-Peak | AJ16: Winter On-Peak | AK16: Winter Off-Peak | AL16: Shoulder On-Peak | AM16: Shoulder Off-Peak | AO16: Res | AP16: Commercial | AQ16: Industrial | AR16: 0 | AS16: 0 | AT16: Res | AU16: Commercial | AV16: Industrial | AW16: 0 | AX16: 0 | AY16: Res | AZ16: Commercial | BA16: Industrial | BB16: 0 | BC16: 0 | BE16: Annual Revenue Requirement | BF16: Annual Native Sales
A17: Type:
M18: Fuel Class: | N18: Natural Gas | O18: Oil | P18: Oil | Q18: Oil | R18: Propane | S18: Propane | T18: Propane | U18: Oil | V18: Oil | BE18: (2026$)
B19: $/kWh | C19: $/kWh | D19: $/kWh | E19: $/kWh | F19: $/kWh | G19: $/kWh | H19: $/kW-yr | I19: $/kW-yr | J19: $/kW-yr | K19: $/kW-yr | N19: $/MMBtu | O19: $/MMBtu | P19: $/MMBtu | Q19: $/MMBtu | R19: $/MMBtu | S19: $/MMBtu | T19: $/MMBtu | U19: $/MMBtu | V19: $/MMBtu | W19: $/MMBtu | X19: $/MMBtu | Y19: $/MMBtu | Z19: $/MMBtu | AA19: $/MMBtu | AB19: $/MMBtu | AC19: $/MMBtu | AE19: $/Gallon | AF19: $/ | AH19: $/kWh | AI19: $/kWh | AJ19: $/kWh | AK19: $/kWh | AL19: $/kWh | AM19: $/kWh | AO19: $/kWh | AP19: $/kWh | AQ19: $/kWh | AR19: $/kWh | AS19: $/kWh | AT19: $/MMBtu | AU19: $/MMBtu | AV19: $/MMBtu | AW19: $/MMBtu | AX19: $/MMBtu | AY19: $/MMBtu | AZ19: $/MMBtu | BA19: $/MMBtu | BB19: $/MMBtu | BC19: $/MMBtu | BE19: $Million | BF19: GWh
A20: 2026 | B20: 0.06 | C20: 0.04 | D20: 0.06 | E20: 0.04 | F20: 0.04 | H20: 89.69 | I20: 0 | J20: 18.6 | K20: 0 | N20: 5.62 | O20: 24.68 | P20: 18.71 | Q20: 18.71 | R20: 25.38 | S20: 22.83 | T20: 22.83 | U20: 28.12 | V20: 27.09 | AE20: 0.017 | AO20: 0.2 | AP20: 0.14 | AQ20: 0.08 | AT20: 11.26 | AU20: 9.77 | AV20: 7.91 | AY20: 24.68 | AZ20: 18.71 | BA20: 18.71
A21: 2027 | B21: 0.06 | C21: 0.05 | D21: 0.06 | E21: 0.05 | F21: 0.04 | H21: 49.6 | I21: 0 | J21: 18.32 | K21: 0 | N21: 4.73 | O21: 25 | P21: 18.24 | Q21: 18.19 | R21: 25.19 | S21: 22.61 | T21: 22.51 | U21: 28.19 | V21: 26.53 | AE21: 0.017 | AO21: 0.21 | AP21: 0.14 | AQ21: 0.08 | AT21: 10.72 | AU21: 9.96 | AV21: 7.69 | AY21: 25 | AZ21: 18.24 | BA21: 18.19
A22: 2028 | B22: 0.06 | C22: 0.05 | D22: 0.06 | E22: 0.05 | F22: 0.04 | H22: 42.36 | I22: 0 | J22: 18.31 | K22: 0 | N22: 4.71 | O22: 25.57 | P22: 17.97 | Q22: 17.87 | R22: 25.19 | S22: 22.75 | T22: 22.7 | U22: 28.53 | V22: 26.25 | AE22: 0.017 | AO22: 0.21 | AP22: 0.14 | AQ22: 0.08 | AT22: 10.38 | AU22: 10.34 | AV22: 7.76 | AY22: 25.57 | AZ22: 17.97 | BA22: 17.87
A23: 2029 | B23: 0.06 | C23: 0.05 | D23: 0.06 | E23: 0.05 | F23: 0.04 | H23: 63.21 | I23: 0 | J23: 18.3 | K23: 0 | N23: 4.59 | O23: 26.19 | P23: 17.72 | Q23: 17.57 | R23: 25.4 | S23: 23.11 | T23: 23.23 | U23: 28.89 | V23: 25.94 | AE23: 0.017 | AO23: 0.22 | AP23: 0.14 | AQ23: 0.08 | AT23: 10.19 | AU23: 10.84 | AV23: 7.94 | AY23: 26.19 | AZ23: 17.72 | BA23: 17.57
A24: 2030 | B24: 0.07 | C24: 0.05 | D24: 0.07 | E24: 0.05 | F24: 0.04 | H24: 57.55 | I24: 0 | J24: 18.29 | K24: 0 | N24: 5.02 | O24: 26.88 | P24: 17.5 | Q24: 17.3 | R24: 25.8 | S24: 23.63 | T24: 23.99 | U24: 29.3 | V24: 26 | AE24: 0.017 | AO24: 0.22 | AP24: 0.15 | AQ24: 0.08 | AT24: 9.98 | AU24: 11.31 | AV24: 8.15 | AY24: 26.88 | AZ24: 17.5 | BA24: 17.3
A25: 2031 | B25: 0.07 | C25: 0.05 | D25: 0.07 | E25: 0.05 | F25: 0.04 | H25: 60.93 | I25: 0 | J25: 18.3 | K25: 0 | N25: 5.02 | O25: 26.98 | P25: 17.56 | Q25: 17.36 | R25: 26.27 | S25: 24.12 | T25: 24.72 | U25: 29.38 | V25: 26.05 | AE25: 0.017 | AO25: 0.22 | AP25: 0.15 | AQ25: 0.08 | AT25: 10.2 | AU25: 11.51 | AV25: 8.37 | AY25: 26.98 | AZ25: 17.56 | BA25: 17.36
A26: 2032 | B26: 0.06 | C26: 0.05 | D26: 0.06 | E26: 0.05 | F26: 0.04 | H26: 74.26 | I26: 0 | J26: 18.29 | K26: 0 | N26: 5.01 | O26: 26.83 | P26: 17.49 | Q26: 17.3 | R26: 27.07 | S26: 25.08 | T26: 26.16 | U26: 29.25 | V26: 25.93 | AE26: 0.017 | AO26: 0.21 | AP26: 0.14 | AQ26: 0.08 | AT26: 10.71 | AU26: 12.01 | AV26: 9.1 | AY26: 26.83 | AZ26: 17.49 | BA26: 17.3
A27: 2033 | B27: 0.06 | C27: 0.05 | D27: 0.06 | E27: 0.05 | F27: 0.04 | H27: 67.34 | I27: 0 | J27: 18.28 | K27: 0 | N27: 5.01 | O27: 27.26 | P27: 17.79 | Q27: 17.6 | R27: 28.12 | S27: 26.22 | T27: 27.91 | U27: 29.67 | V27: 25.83 | AE27: 0.017 | AO27: 0.22 | AP27: 0.14 | AQ27: 0.08 | AT27: 11.18 | AU27: 12.46 | AV27: 9.66 | AY27: 27.26 | AZ27: 17.79 | BA27: 17.6
A28: 2034 | B28: 0.06 | C28: 0.05 | D28: 0.06 | E28: 0.05 | F28: 0.04 | H28: 74.77 | I28: 0 | J28: 18.27 | K28: 0 | N28: 5 | O28: 27.43 | P28: 17.92 | Q28: 17.73 | R28: 29.04 | S28: 26.97 | T28: 29.09 | U28: 29.84 | V28: 25.92 | AE28: 0.017 | AO28: 0.22 | AP28: 0.14 | AQ28: 0.08 | AT28: 11.49 | AU28: 12.72 | AV28: 9.95 | AY28: 27.43 | AZ28: 17.92 | BA28: 17.73
A29: 2035 | B29: 0.06 | C29: 0.05 | D29: 0.06 | E29: 0.05 | F29: 0.04 | H29: 81.46 | I29: 0 | J29: 18.25 | K29: 0 | N29: 5 | O29: 27.65 | P29: 18.13 | Q29: 17.94 | R29: 29.7 | S29: 27.32 | T29: 29.66 | U29: 30.15 | V29: 25.71 | AE29: 0.017 | AO29: 0.22 | AP29: 0.15 | AQ29: 0.08 | AT29: 11.66 | AU29: 12.84 | AV29: 10.06 | AY29: 27.65 | AZ29: 18.13 | BA29: 17.94
A30: 2036 | B30: 0.06 | C30: 0.05 | D30: 0.06 | E30: 0.05 | F30: 0.04 | H30: 85.29 | I30: 0 | J30: 18.25 | K30: 0 | N30: 5 | O30: 27.69 | P30: 18.21 | Q30: 18.03 | R30: 30.1 | S30: 27.43 | T30: 29.84 | U30: 30.25 | V30: 25.73 | AE30: 0.017 | AO30: 0.21 | AP30: 0.14 | AQ30: 0.08 | AT30: 11.71 | AU30: 12.83 | AV30: 10.02 | AY30: 27.69 | AZ30: 18.21 | BA30: 18.03
A31: 2037 | B31: 0.06 | C31: 0.05 | D31: 0.06 | E31: 0.05 | F31: 0.04 | H31: 87.17 | I31: 0 | J31: 18.24 | K31: 0 | N31: 4.99 | O31: 27.91 | P31: 18.38 | Q31: 18.21 | R31: 30.32 | S31: 27.46 | T31: 29.89 | U31: 30.47 | V31: 25.65 | AE31: 0.017 | AO31: 0.22 | AP31: 0.14 | AQ31: 0.08 | AT31: 11.68 | AU31: 12.75 | AV31: 9.87 | AY31: 27.91 | AZ31: 18.38 | BA31: 18.21
... A69: 2075 | B69: 0.08 | C69: 0.06 | D69: 0.08 | E69: 0.06 | F69: 0.05 | H69: 81.71 | I69: 0 | J69: 17.1 | K69: 0 | N69: 4.68 | O69: 31.29 | P69: 20.55 | Q69: 20.34 | R69: 33.23 | S69: 29.95 | T69: 33.93 | U69: 33.13 | V69: 23.79 | AE69: 0.017 | AO69: 0.25 | AP69: 0.17 | AQ69: 0.09 | AT69: 12.35 | AU69: 12.92 | AV69: 9.61 | AY69: 31.29 | AZ69: 20.55 | BA69: 20.34
